Compiled from "Jack_the_Parser_Generator.java"
public class spec.benchmarks._228_jack.Jack_the_Parser_Generator extends spec.benchmarks._228_jack.Jack_the_Parser_Generator_Internals implements spec.benchmarks._228_jack.Jack_the_Parser_GeneratorConstants{
static final int lookahead;

private int parse_error_count;

private spec.benchmarks._228_jack.TokenManager token_source;

private spec.benchmarks._228_jack.Token token;

private spec.benchmarks._228_jack.TrueException etrue;

private spec.benchmarks._228_jack.FalseException efalse;

private int la;

private int index;

private boolean cond;

public spec.benchmarks._228_jack.Jack_the_Parser_Generator(java.io.DataInputStream);
  Code:
   0:	aload_0
   1:	invokespecial	#85; //Method spec/benchmarks/_228_jack/Jack_the_Parser_Generator_Internals."<init>":()V
   4:	aload_0
   5:	new	#72; //class TrueException
   8:	dup
   9:	invokespecial	#102; //Method spec/benchmarks/_228_jack/TrueException."<init>":()V
   12:	putfield	#267; //Field etrue:Lspec/benchmarks/_228_jack/TrueException;
   15:	aload_0
   16:	new	#44; //class FalseException
   19:	dup
   20:	invokespecial	#83; //Method spec/benchmarks/_228_jack/FalseException."<init>":()V
   23:	putfield	#262; //Field efalse:Lspec/benchmarks/_228_jack/FalseException;
   26:	new	#39; //class CharPosInputStream
   29:	dup
   30:	aload_1
   31:	iconst_1
   32:	iconst_1
   33:	invokespecial	#105; //Method spec/benchmarks/_228_jack/CharPosInputStream."<init>":(Ljava/io/DataInputStream;II)V
   36:	astore_2
   37:	aload_0
   38:	new	#48; //class Jack_the_Parser_GeneratorTokenManager
   41:	dup
   42:	aload_2
   43:	invokespecial	#107; //Method spec/benchmarks/_228_jack/Jack_the_Parser_GeneratorTokenManager."<init>":(Lspec/benchmarks/_228_jack/CharStream;)V
   46:	putfield	#321; //Field token_source:Lspec/benchmarks/_228_jack/TokenManager;
   49:	return

public spec.benchmarks._228_jack.Jack_the_Parser_Generator(spec.benchmarks._228_jack.TokenManager);
  Code:
   0:	aload_0
   1:	invokespecial	#85; //Method spec/benchmarks/_228_jack/Jack_the_Parser_Generator_Internals."<init>":()V
   4:	aload_0
   5:	new	#72; //class TrueException
   8:	dup
   9:	invokespecial	#102; //Method spec/benchmarks/_228_jack/TrueException."<init>":()V
   12:	putfield	#267; //Field etrue:Lspec/benchmarks/_228_jack/TrueException;
   15:	aload_0
   16:	new	#44; //class FalseException
   19:	dup
   20:	invokespecial	#83; //Method spec/benchmarks/_228_jack/FalseException."<init>":()V
   23:	putfield	#262; //Field efalse:Lspec/benchmarks/_228_jack/FalseException;
   26:	aload_0
   27:	aload_1
   28:	putfield	#321; //Field token_source:Lspec/benchmarks/_228_jack/TokenManager;
   31:	return

public void parse_error(java.lang.String);
  Code:
   0:	aload_0
   1:	getfield	#321; //Field token_source:Lspec/benchmarks/_228_jack/TokenManager;
   4:	iconst_0
   5:	invokeinterface	#277,  2; //InterfaceMethod spec/benchmarks/_228_jack/TokenManager.getToken:(I)Lspec/benchmarks/_228_jack/Token;
   10:	astore_2
   11:	getstatic	#266; //Field java/lang/System.err:Ljava/io/PrintStream;
   14:	new	#34; //class StringBuffer
   17:	dup
   18:	ldc	#16; //String Error: Line 
   20:	invokespecial	#106; //Method java/lang/StringBuffer."<init>":(Ljava/lang/String;)V
   23:	aload_2
   24:	getfield	#238; //Field spec/benchmarks/_228_jack/Token.beginLine:I
   27:	invokevirtual	#234; //Method java/lang/StringBuffer.append:(I)Ljava/lang/StringBuffer;
   30:	ldc	#5; //String , Column 
   32:	invokevirtual	#235; //Method java/lang/StringBuffer.append:(Ljava/lang/String;)Ljava/lang/StringBuffer;
   35:	aload_2
   36:	getfield	#237; //Field spec/benchmarks/_228_jack/Token.beginColumn:I
   39:	invokevirtual	#234; //Method java/lang/StringBuffer.append:(I)Ljava/lang/StringBuffer;
   42:	ldc	#8; //String : 
   44:	invokevirtual	#235; //Method java/lang/StringBuffer.append:(Ljava/lang/String;)Ljava/lang/StringBuffer;
   47:	aload_1
   48:	invokevirtual	#235; //Method java/lang/StringBuffer.append:(Ljava/lang/String;)Ljava/lang/StringBuffer;
   51:	invokevirtual	#317; //Method java/lang/StringBuffer.toString:()Ljava/lang/String;
   54:	invokevirtual	#301; //Method java/io/PrintStream.println:(Ljava/lang/String;)V
   57:	goto	83
   60:	pop
   61:	getstatic	#266; //Field java/lang/System.err:Ljava/io/PrintStream;
   64:	new	#34; //class StringBuffer
   67:	dup
   68:	ldc	#15; //String Error: 
   70:	invokespecial	#106; //Method java/lang/StringBuffer."<init>":(Ljava/lang/String;)V
   73:	aload_1
   74:	invokevirtual	#235; //Method java/lang/StringBuffer.append:(Ljava/lang/String;)Ljava/lang/StringBuffer;
   77:	invokevirtual	#317; //Method java/lang/StringBuffer.toString:()Ljava/lang/String;
   80:	invokevirtual	#301; //Method java/io/PrintStream.println:(Ljava/lang/String;)V
   83:	aload_0
   84:	dup
   85:	getfield	#300; //Field parse_error_count:I
   88:	iconst_1
   89:	iadd
   90:	putfield	#300; //Field parse_error_count:I
   93:	return
  Exception table:
   from   to  target type
     0    57    60   Class java/lang/Exception


public int get_parse_error_count();
  Code:
   0:	aload_0
   1:	getfield	#300; //Field parse_error_count:I
   4:	ireturn

private void etrue_thrower();
   throws spec/benchmarks/_228_jack/TrueException
  Code:
   0:	aload_0
   1:	getfield	#267; //Field etrue:Lspec/benchmarks/_228_jack/TrueException;
   4:	athrow

private void consume_token(int);
   throws spec/benchmarks/_228_jack/ParseError
  Code:
   0:	aload_0
   1:	aload_0
   2:	getfield	#321; //Field token_source:Lspec/benchmarks/_228_jack/TokenManager;
   5:	invokeinterface	#276,  1; //InterfaceMethod spec/benchmarks/_228_jack/TokenManager.getNextToken:()Lspec/benchmarks/_228_jack/Token;
   10:	putfield	#318; //Field token:Lspec/benchmarks/_228_jack/Token;
   13:	aload_0
   14:	getfield	#318; //Field token:Lspec/benchmarks/_228_jack/Token;
   17:	getfield	#288; //Field spec/benchmarks/_228_jack/Token.kind:I
   20:	iload_1
   21:	if_icmpne	25
   24:	return
   25:	aload_0
   26:	iload_1
   27:	aload_0
   28:	getfield	#318; //Field token:Lspec/benchmarks/_228_jack/Token;
   31:	invokespecial	#320; //Method token_error:(ILspec/benchmarks/_228_jack/Token;)V
   34:	new	#54; //class ParseError
   37:	dup
   38:	invokespecial	#89; //Method spec/benchmarks/_228_jack/ParseError."<init>":()V
   41:	athrow
   42:	pop
   43:	aload_0
   44:	iload_1
   45:	invokespecial	#319; //Method token_eof_error:(I)V
   48:	new	#54; //class ParseError
   51:	dup
   52:	invokespecial	#89; //Method spec/benchmarks/_228_jack/ParseError."<init>":()V
   55:	athrow
  Exception table:
   from   to  target type
     0    42    42   Class spec/benchmarks/_228_jack/TokenException


private void scan_token(int);
   throws spec/benchmarks/_228_jack/TrueException, spec/benchmarks/_228_jack/FalseException
  Code:
   0:	aload_0
   1:	aload_0
   2:	getfield	#321; //Field token_source:Lspec/benchmarks/_228_jack/TokenManager;
   5:	aload_0
   6:	getfield	#281; //Field index:I
   9:	invokeinterface	#277,  2; //InterfaceMethod spec/benchmarks/_228_jack/TokenManager.getToken:(I)Lspec/benchmarks/_228_jack/Token;
   14:	putfield	#318; //Field token:Lspec/benchmarks/_228_jack/Token;
   17:	aload_0
   18:	getfield	#318; //Field token:Lspec/benchmarks/_228_jack/Token;
   21:	getfield	#288; //Field spec/benchmarks/_228_jack/Token.kind:I
   24:	iload_1
   25:	if_icmpeq	33
   28:	aload_0
   29:	getfield	#262; //Field efalse:Lspec/benchmarks/_228_jack/FalseException;
   32:	athrow
   33:	aload_0
   34:	dup
   35:	getfield	#289; //Field la:I
   38:	iconst_1
   39:	isub
   40:	dup_x1
   41:	putfield	#289; //Field la:I
   44:	ifne	52
   47:	aload_0
   48:	getfield	#267; //Field etrue:Lspec/benchmarks/_228_jack/TrueException;
   51:	athrow
   52:	aload_0
   53:	dup
   54:	getfield	#281; //Field index:I
   57:	iconst_1
   58:	iadd
   59:	putfield	#281; //Field index:I
   62:	return
   63:	pop
   64:	aload_0
   65:	getfield	#262; //Field efalse:Lspec/benchmarks/_228_jack/FalseException;
   68:	athrow
  Exception table:
   from   to  target type
     0    62    63   Class spec/benchmarks/_228_jack/TokenException


private void choice_error(java.lang.String);
  Code:
   0:	getstatic	#297; //Field spec/harness/Context.out:Ljava/io/PrintStream;
   3:	new	#34; //class StringBuffer
   6:	dup
   7:	ldc	#18; //String Token stream does not offer expansion choice for 
   9:	invokespecial	#106; //Method java/lang/StringBuffer."<init>":(Ljava/lang/String;)V
   12:	aload_1
   13:	invokevirtual	#235; //Method java/lang/StringBuffer.append:(Ljava/lang/String;)Ljava/lang/StringBuffer;
   16:	invokevirtual	#317; //Method java/lang/StringBuffer.toString:()Ljava/lang/String;
   19:	invokevirtual	#301; //Method java/io/PrintStream.println:(Ljava/lang/String;)V
   22:	aload_0
   23:	getfield	#321; //Field token_source:Lspec/benchmarks/_228_jack/TokenManager;
   26:	iconst_0
   27:	invokeinterface	#277,  2; //InterfaceMethod spec/benchmarks/_228_jack/TokenManager.getToken:(I)Lspec/benchmarks/_228_jack/Token;
   32:	astore_2
   33:	getstatic	#297; //Field spec/harness/Context.out:Ljava/io/PrintStream;
   36:	ldc	#17; //String The last token successfully scanned is:
   38:	invokevirtual	#301; //Method java/io/PrintStream.println:(Ljava/lang/String;)V
   41:	getstatic	#297; //Field spec/harness/Context.out:Ljava/io/PrintStream;
   44:	new	#34; //class StringBuffer
   47:	dup
   48:	ldc	#3; //String     <kind=
   50:	invokespecial	#106; //Method java/lang/StringBuffer."<init>":(Ljava/lang/String;)V
   53:	aload_2
   54:	getfield	#288; //Field spec/benchmarks/_228_jack/Token.kind:I
   57:	invokevirtual	#234; //Method java/lang/StringBuffer.append:(I)Ljava/lang/StringBuffer;
   60:	ldc	#10; //String ; bline=
   62:	invokevirtual	#235; //Method java/lang/StringBuffer.append:(Ljava/lang/String;)Ljava/lang/StringBuffer;
   65:	aload_2
   66:	getfield	#238; //Field spec/benchmarks/_228_jack/Token.beginLine:I
   69:	invokevirtual	#234; //Method java/lang/StringBuffer.append:(I)Ljava/lang/StringBuffer;
   72:	ldc	#9; //String ; bcolumn=
   74:	invokevirtual	#235; //Method java/lang/StringBuffer.append:(Ljava/lang/String;)Ljava/lang/StringBuffer;
   77:	aload_2
   78:	getfield	#237; //Field spec/benchmarks/_228_jack/Token.beginColumn:I
   81:	invokevirtual	#234; //Method java/lang/StringBuffer.append:(I)Ljava/lang/StringBuffer;
   84:	ldc	#12; //String ; eline=
   86:	invokevirtual	#235; //Method java/lang/StringBuffer.append:(Ljava/lang/String;)Ljava/lang/StringBuffer;
   89:	aload_2
   90:	getfield	#264; //Field spec/benchmarks/_228_jack/Token.endLine:I
   93:	invokevirtual	#234; //Method java/lang/StringBuffer.append:(I)Ljava/lang/StringBuffer;
   96:	ldc	#11; //String ; ecolumn=
   98:	invokevirtual	#235; //Method java/lang/StringBuffer.append:(Ljava/lang/String;)Ljava/lang/StringBuffer;
   101:	aload_2
   102:	getfield	#263; //Field spec/benchmarks/_228_jack/Token.endColumn:I
   105:	invokevirtual	#234; //Method java/lang/StringBuffer.append:(I)Ljava/lang/StringBuffer;
   108:	ldc	#13; //String ; image=\"
   110:	invokevirtual	#235; //Method java/lang/StringBuffer.append:(Ljava/lang/String;)Ljava/lang/StringBuffer;
   113:	aload_2
   114:	getfield	#280; //Field spec/benchmarks/_228_jack/Token.image:Ljava/lang/String;
   117:	invokevirtual	#235; //Method java/lang/StringBuffer.append:(Ljava/lang/String;)Ljava/lang/StringBuffer;
   120:	ldc	#4; //String \">
   122:	invokevirtual	#235; //Method java/lang/StringBuffer.append:(Ljava/lang/String;)Ljava/lang/StringBuffer;
   125:	invokevirtual	#317; //Method java/lang/StringBuffer.toString:()Ljava/lang/String;
   128:	invokevirtual	#301; //Method java/io/PrintStream.println:(Ljava/lang/String;)V
   131:	return
   132:	pop
   133:	getstatic	#297; //Field spec/harness/Context.out:Ljava/io/PrintStream;
   136:	ldc	#14; //String Currently at beginning of stream - no tokens successfully scanned yet.
   138:	invokevirtual	#301; //Method java/io/PrintStream.println:(Ljava/lang/String;)V
   141:	return
  Exception table:
   from   to  target type
    22   131   132   Class spec/benchmarks/_228_jack/TokenException


private void token_error(int,spec.benchmarks._228_jack.Token);
  Code:
   0:	getstatic	#297; //Field spec/harness/Context.out:Ljava/io/PrintStream;
   3:	new	#34; //class StringBuffer
   6:	dup
   7:	ldc	#19; //String Was expecting token of kind 
   9:	invokespecial	#106; //Method java/lang/StringBuffer."<init>":(Ljava/lang/String;)V
   12:	iload_1
   13:	invokevirtual	#234; //Method java/lang/StringBuffer.append:(I)Ljava/lang/StringBuffer;
   16:	ldc	#6; //String , but got:
   18:	invokevirtual	#235; //Method java/lang/StringBuffer.append:(Ljava/lang/String;)Ljava/lang/StringBuffer;
   21:	invokevirtual	#317; //Method java/lang/StringBuffer.toString:()Ljava/lang/String;
   24:	invokevirtual	#301; //Method java/io/PrintStream.println:(Ljava/lang/String;)V
   27:	getstatic	#297; //Field spec/harness/Context.out:Ljava/io/PrintStream;
   30:	new	#34; //class StringBuffer
   33:	dup
   34:	ldc	#3; //String     <kind=
   36:	invokespecial	#106; //Method java/lang/StringBuffer."<init>":(Ljava/lang/String;)V
   39:	aload_2
   40:	getfield	#288; //Field spec/benchmarks/_228_jack/Token.kind:I
   43:	invokevirtual	#234; //Method java/lang/StringBuffer.append:(I)Ljava/lang/StringBuffer;
   46:	ldc	#10; //String ; bline=
   48:	invokevirtual	#235; //Method java/lang/StringBuffer.append:(Ljava/lang/String;)Ljava/lang/StringBuffer;
   51:	aload_2
   52:	getfield	#238; //Field spec/benchmarks/_228_jack/Token.beginLine:I
   55:	invokevirtual	#234; //Method java/lang/StringBuffer.append:(I)Ljava/lang/StringBuffer;
   58:	ldc	#9; //String ; bcolumn=
   60:	invokevirtual	#235; //Method java/lang/StringBuffer.append:(Ljava/lang/String;)Ljava/lang/StringBuffer;
   63:	aload_2
   64:	getfield	#237; //Field spec/benchmarks/_228_jack/Token.beginColumn:I
   67:	invokevirtual	#234; //Method java/lang/StringBuffer.append:(I)Ljava/lang/StringBuffer;
   70:	ldc	#12; //String ; eline=
   72:	invokevirtual	#235; //Method java/lang/StringBuffer.append:(Ljava/lang/String;)Ljava/lang/StringBuffer;
   75:	aload_2
   76:	getfield	#264; //Field spec/benchmarks/_228_jack/Token.endLine:I
   79:	invokevirtual	#234; //Method java/lang/StringBuffer.append:(I)Ljava/lang/StringBuffer;
   82:	ldc	#11; //String ; ecolumn=
   84:	invokevirtual	#235; //Method java/lang/StringBuffer.append:(Ljava/lang/String;)Ljava/lang/StringBuffer;
   87:	aload_2
   88:	getfield	#263; //Field spec/benchmarks/_228_jack/Token.endColumn:I
   91:	invokevirtual	#234; //Method java/lang/StringBuffer.append:(I)Ljava/lang/StringBuffer;
   94:	ldc	#13; //String ; image=\"
   96:	invokevirtual	#235; //Method java/lang/StringBuffer.append:(Ljava/lang/String;)Ljava/lang/StringBuffer;
   99:	aload_2
   100:	getfield	#280; //Field spec/benchmarks/_228_jack/Token.image:Ljava/lang/String;
   103:	invokevirtual	#235; //Method java/lang/StringBuffer.append:(Ljava/lang/String;)Ljava/lang/StringBuffer;
   106:	ldc	#4; //String \">
   108:	invokevirtual	#235; //Method java/lang/StringBuffer.append:(Ljava/lang/String;)Ljava/lang/StringBuffer;
   111:	invokevirtual	#317; //Method java/lang/StringBuffer.toString:()Ljava/lang/String;
   114:	invokevirtual	#301; //Method java/io/PrintStream.println:(Ljava/lang/String;)V
   117:	return

private void token_eof_error(int);
  Code:
   0:	getstatic	#297; //Field spec/harness/Context.out:Ljava/io/PrintStream;
   3:	new	#34; //class StringBuffer
   6:	dup
   7:	ldc	#19; //String Was expecting token of kind 
   9:	invokespecial	#106; //Method java/lang/StringBuffer."<init>":(Ljava/lang/String;)V
   12:	iload_1
   13:	invokevirtual	#234; //Method java/lang/StringBuffer.append:(I)Ljava/lang/StringBuffer;
   16:	ldc	#7; //String , but reached end of file.
   18:	invokevirtual	#235; //Method java/lang/StringBuffer.append:(Ljava/lang/String;)Ljava/lang/StringBuffer;
   21:	invokevirtual	#317; //Method java/lang/StringBuffer.toString:()Ljava/lang/String;
   24:	invokevirtual	#301; //Method java/io/PrintStream.println:(Ljava/lang/String;)V
   27:	return

public void jack_input();
   throws spec/benchmarks/_228_jack/ParseError
  Code:
   0:	iconst_1
   1:	istore_1
   2:	iconst_0
   3:	istore_2
   4:	iconst_0
   5:	istore_3
   6:	goto	146
   9:	aload_0
   10:	bipush	15
   12:	iconst_1
   13:	invokespecial	#119; //Method _Jack2_2:(II)Z
   16:	ifeq	50
   19:	aload_0
   20:	bipush	114
   22:	invokespecial	#253; //Method consume_token:(I)V
   25:	aload_0
   26:	bipush	77
   28:	invokespecial	#253; //Method consume_token:(I)V
   31:	aload_0
   32:	invokevirtual	#282; //Method integer_literal:()I
   35:	istore_1
   36:	aload_0
   37:	bipush	74
   39:	invokespecial	#253; //Method consume_token:(I)V
   42:	aload_0
   43:	iload_1
   44:	invokevirtual	#290; //Method spec/benchmarks/_228_jack/Jack_the_Parser_Generator_Internals.la_bookkeep:(I)V
   47:	goto	146
   50:	aload_0
   51:	bipush	15
   53:	iconst_1
   54:	invokespecial	#130; //Method _Jack2_3:(II)Z
   57:	ifeq	91
   60:	aload_0
   61:	bipush	115
   63:	invokespecial	#253; //Method consume_token:(I)V
   66:	aload_0
   67:	bipush	77
   69:	invokespecial	#253; //Method consume_token:(I)V
   72:	aload_0
   73:	invokevirtual	#239; //Method boolean_literal:()Z
   76:	istore_2
   77:	aload_0
   78:	bipush	74
   80:	invokespecial	#253; //Method consume_token:(I)V
   83:	aload_0
   84:	iload_2
   85:	invokevirtual	#315; //Method spec/benchmarks/_228_jack/Jack_the_Parser_Generator_Internals.st_bookkeep:(Z)V
   88:	goto	146
   91:	aload_0
   92:	bipush	15
   94:	iconst_1
   95:	invokespecial	#141; //Method _Jack2_4:(II)Z
   98:	ifeq	132
   101:	aload_0
   102:	bipush	116
   104:	invokespecial	#253; //Method consume_token:(I)V
   107:	aload_0
   108:	bipush	77
   110:	invokespecial	#253; //Method consume_token:(I)V
   113:	aload_0
   114:	invokevirtual	#239; //Method boolean_literal:()Z
   117:	istore_3
   118:	aload_0
   119:	bipush	74
   121:	invokespecial	#253; //Method consume_token:(I)V
   124:	aload_0
   125:	iload_3
   126:	invokevirtual	#322; //Method spec/benchmarks/_228_jack/Jack_the_Parser_Generator_Internals.tt_bookkeep:(Z)V
   129:	goto	146
   132:	aload_0
   133:	ldc	#23; //String jack_input
   135:	invokespecial	#244; //Method choice_error:(Ljava/lang/String;)V
   138:	new	#54; //class ParseError
   141:	dup
   142:	invokespecial	#89; //Method spec/benchmarks/_228_jack/ParseError."<init>":()V
   145:	athrow
   146:	aload_0
   147:	bipush	15
   149:	iconst_1
   150:	invokespecial	#108; //Method _Jack2_1:(II)Z
   153:	ifne	9
   156:	aload_0
   157:	iload_1
   158:	iload_2
   159:	iload_3
   160:	invokevirtual	#275; //Method spec/benchmarks/_228_jack/Jack_the_Parser_Generator_Internals.flags_finalize:(IZZ)V
   163:	aload_0
   164:	invokevirtual	#256; //Method spec/benchmarks/_228_jack/Jack_the_Parser_Generator_Internals.db_init:()V
   167:	aload_0
   168:	bipush	117
   170:	invokespecial	#253; //Method consume_token:(I)V
   173:	aload_0
   174:	bipush	68
   176:	invokespecial	#253; //Method consume_token:(I)V
   179:	aload_0
   180:	invokevirtual	#278; //Method identifier:()Ljava/lang/String;
   183:	astore	4
   185:	aload_0
   186:	aload	4
   188:	invokevirtual	#258; //Method spec/benchmarks/_228_jack/Jack_the_Parser_Generator_Internals.db_namecu:(Ljava/lang/String;)V
   191:	aload_0
   192:	bipush	69
   194:	invokespecial	#253; //Method consume_token:(I)V
   197:	aload_0
   198:	aload	4
   200:	invokevirtual	#283; //Method java_compilation_unit:(Ljava/lang/String;)V
   203:	aload_0
   204:	bipush	118
   206:	invokespecial	#253; //Method consume_token:(I)V
   209:	aload_0
   210:	bipush	68
   212:	invokespecial	#253; //Method consume_token:(I)V
   215:	aload_0
   216:	invokevirtual	#278; //Method identifier:()Ljava/lang/String;
   219:	astore	5
   221:	aload_0
   222:	aload	4
   224:	aload	5
   226:	invokevirtual	#248; //Method spec/benchmarks/_228_jack/Jack_the_Parser_Generator_Internals.compare:(Ljava/lang/String;Ljava/lang/String;)V
   229:	aload_0
   230:	bipush	69
   232:	invokespecial	#253; //Method consume_token:(I)V
   235:	aload_0
   236:	invokevirtual	#302; //Method production:()V
   239:	aload_0
   240:	bipush	15
   242:	iconst_1
   243:	invokespecial	#152; //Method _Jack2_5:(II)Z
   246:	ifne	235
   249:	goto	252
   252:	aload_0
   253:	iconst_0
   254:	invokespecial	#253; //Method consume_token:(I)V
   257:	aload_0
   258:	invokevirtual	#259; //Method spec/benchmarks/_228_jack/Jack_the_Parser_Generator_Internals.db_process:()V
   261:	return

public int integer_literal();
   throws spec/benchmarks/_228_jack/ParseError
  Code:
   0:	aload_0
   1:	bipush	65
   3:	invokespecial	#253; //Method consume_token:(I)V
   6:	aload_0
   7:	getfield	#318; //Field token:Lspec/benchmarks/_228_jack/Token;
   10:	getfield	#280; //Field spec/benchmarks/_228_jack/Token.image:Ljava/lang/String;
   13:	invokestatic	#299; //Method java/lang/Integer.parseInt:(Ljava/lang/String;)I
   16:	ireturn
   17:	pop
   18:	new	#29; //class Error
   21:	dup
   22:	invokespecial	#76; //Method java/lang/Error."<init>":()V
   25:	athrow
  Exception table:
   from   to  target type
     6    17    17   Class java/lang/NumberFormatException


public boolean boolean_literal();
   throws spec/benchmarks/_228_jack/ParseError
  Code:
   0:	aload_0
   1:	bipush	15
   3:	iconst_1
   4:	invokespecial	#158; //Method _Jack2_6:(II)Z
   7:	ifeq	18
   10:	aload_0
   11:	bipush	63
   13:	invokespecial	#253; //Method consume_token:(I)V
   16:	iconst_1
   17:	ireturn
   18:	aload_0
   19:	bipush	15
   21:	iconst_1
   22:	invokespecial	#159; //Method _Jack2_7:(II)Z
   25:	ifeq	36
   28:	aload_0
   29:	bipush	64
   31:	invokespecial	#253; //Method consume_token:(I)V
   34:	iconst_0
   35:	ireturn
   36:	aload_0
   37:	ldc	#20; //String boolean_literal
   39:	invokespecial	#244; //Method choice_error:(Ljava/lang/String;)V
   42:	new	#54; //class ParseError
   45:	dup
   46:	invokespecial	#89; //Method spec/benchmarks/_228_jack/ParseError."<init>":()V
   49:	athrow

void java_compilation_unit(java.lang.String);
   throws spec/benchmarks/_228_jack/ParseError
  Code:
   0:	iconst_0
   1:	istore_3
   2:	iconst_0
   3:	istore	4
   5:	aload_0
   6:	getfield	#321; //Field token_source:Lspec/benchmarks/_228_jack/TokenManager;
   9:	iconst_1
   10:	invokeinterface	#277,  2; //InterfaceMethod spec/benchmarks/_228_jack/TokenManager.getToken:(I)Lspec/benchmarks/_228_jack/Token;
   15:	astore_2
   16:	aload_2
   17:	getfield	#288; //Field spec/benchmarks/_228_jack/Token.kind:I
   20:	bipush	118
   22:	if_icmpeq	162
   25:	aload_2
   26:	getfield	#288; //Field spec/benchmarks/_228_jack/Token.kind:I
   29:	bipush	70
   31:	if_icmpne	51
   34:	iload_3
   35:	ifne	48
   38:	iload	4
   40:	ifeq	48
   43:	aload_0
   44:	iconst_1
   45:	invokevirtual	#260; //Method spec/benchmarks/_228_jack/Jack_the_Parser_Generator_Internals.db_setinsertionpoint:(I)V
   48:	iinc	3, 1
   51:	aload_2
   52:	getfield	#288; //Field spec/benchmarks/_228_jack/Token.kind:I
   55:	bipush	71
   57:	if_icmpne	84
   60:	iload_3
   61:	ifeq	67
   64:	iinc	3, -1
   67:	iload_3
   68:	ifne	84
   71:	iload	4
   73:	ifeq	84
   76:	iconst_0
   77:	istore	4
   79:	aload_0
   80:	iconst_2
   81:	invokevirtual	#260; //Method spec/benchmarks/_228_jack/Jack_the_Parser_Generator_Internals.db_setinsertionpoint:(I)V
   84:	aload_0
   85:	getfield	#321; //Field token_source:Lspec/benchmarks/_228_jack/TokenManager;
   88:	invokeinterface	#276,  1; //InterfaceMethod spec/benchmarks/_228_jack/TokenManager.getNextToken:()Lspec/benchmarks/_228_jack/Token;
   93:	astore_2
   94:	aload_0
   95:	aload_2
   96:	invokevirtual	#254; //Method spec/benchmarks/_228_jack/Jack_the_Parser_Generator_Internals.db_addcutoken:(Lspec/benchmarks/_228_jack/Token;)V
   99:	iload_3
   100:	ifne	5
   103:	aload_2
   104:	getfield	#288; //Field spec/benchmarks/_228_jack/Token.kind:I
   107:	bipush	15
   109:	if_icmpne	5
   112:	aload_0
   113:	getfield	#321; //Field token_source:Lspec/benchmarks/_228_jack/TokenManager;
   116:	iconst_1
   117:	invokeinterface	#277,  2; //InterfaceMethod spec/benchmarks/_228_jack/TokenManager.getToken:(I)Lspec/benchmarks/_228_jack/Token;
   122:	getfield	#288; //Field spec/benchmarks/_228_jack/Token.kind:I
   125:	bipush	118
   127:	if_icmpeq	162
   130:	aload_0
   131:	getfield	#321; //Field token_source:Lspec/benchmarks/_228_jack/TokenManager;
   134:	invokeinterface	#276,  1; //InterfaceMethod spec/benchmarks/_228_jack/TokenManager.getNextToken:()Lspec/benchmarks/_228_jack/Token;
   139:	astore_2
   140:	aload_0
   141:	aload_2
   142:	invokevirtual	#254; //Method spec/benchmarks/_228_jack/Jack_the_Parser_Generator_Internals.db_addcutoken:(Lspec/benchmarks/_228_jack/Token;)V
   145:	aload_2
   146:	getfield	#280; //Field spec/benchmarks/_228_jack/Token.image:Ljava/lang/String;
   149:	aload_1
   150:	invokevirtual	#265; //Method java/lang/String.equals:(Ljava/lang/Object;)Z
   153:	ifeq	5
   156:	iconst_1
   157:	istore	4
   159:	goto	5
   162:	aload_0
   163:	invokevirtual	#257; //Method spec/benchmarks/_228_jack/Jack_the_Parser_Generator_Internals.db_insertionpointerrors:()V
   166:	return
   167:	pop
   168:	new	#54; //class ParseError
   171:	dup
   172:	invokespecial	#89; //Method spec/benchmarks/_228_jack/ParseError."<init>":()V
   175:	athrow
  Exception table:
   from   to  target type
     0   166   167   Class spec/benchmarks/_228_jack/TokenException


public void production();
   throws spec/benchmarks/_228_jack/ParseError
  Code:
   0:	new	#42; //class Container
   3:	dup
   4:	invokespecial	#82; //Method spec/benchmarks/_228_jack/Container."<init>":()V
   7:	astore_3
   8:	new	#36; //class Vector
   11:	dup
   12:	invokespecial	#77; //Method java/util/Vector."<init>":()V
   15:	astore	4
   17:	aload_0
   18:	bipush	15
   20:	iconst_1
   21:	invokespecial	#160; //Method _Jack2_8:(II)Z
   24:	ifeq	117
   27:	aload_0
   28:	bipush	119
   30:	invokespecial	#253; //Method consume_token:(I)V
   33:	new	#50; //class JavaCodeProduction
   36:	dup
   37:	invokespecial	#86; //Method spec/benchmarks/_228_jack/JavaCodeProduction."<init>":()V
   40:	astore_2
   41:	aload_0
   42:	aload_2
   43:	checkcast	#52; //class NormalProduction
   46:	getfield	#310; //Field spec/benchmarks/_228_jack/NormalProduction.return_type_tokens:Ljava/util/Vector;
   49:	invokevirtual	#287; //Method java_return_type:(Ljava/util/Vector;)V
   52:	aload_0
   53:	invokevirtual	#278; //Method identifier:()Ljava/lang/String;
   56:	astore_1
   57:	aload_2
   58:	checkcast	#52; //class NormalProduction
   61:	aload_1
   62:	invokevirtual	#314; //Method spec/benchmarks/_228_jack/NormalProduction.setlhs:(Ljava/lang/String;)V
   65:	aload_0
   66:	bipush	68
   68:	invokespecial	#253; //Method consume_token:(I)V
   71:	aload_0
   72:	aload_2
   73:	checkcast	#52; //class NormalProduction
   76:	getfield	#298; //Field spec/benchmarks/_228_jack/NormalProduction.parameter_list_tokens:Ljava/util/Vector;
   79:	invokevirtual	#286; //Method java_parameter_list:(Ljava/util/Vector;)V
   82:	aload_0
   83:	bipush	69
   85:	invokespecial	#253; //Method consume_token:(I)V
   88:	aload_0
   89:	bipush	70
   91:	invokespecial	#253; //Method consume_token:(I)V
   94:	aload_0
   95:	aload_2
   96:	checkcast	#50; //class JavaCodeProduction
   99:	getfield	#247; //Field spec/benchmarks/_228_jack/JavaCodeProduction.code_tokens:Ljava/util/Vector;
   102:	invokevirtual	#284; //Method java_declarations_and_code:(Ljava/util/Vector;)V
   105:	aload_0
   106:	bipush	71
   108:	invokespecial	#253; //Method consume_token:(I)V
   111:	aload_0
   112:	aload_2
   113:	invokevirtual	#255; //Method spec/benchmarks/_228_jack/Jack_the_Parser_Generator_Internals.db_addproduction:(Lspec/benchmarks/_228_jack/Production;)V
   116:	return
   117:	aload_0
   118:	bipush	15
   120:	iconst_1
   121:	invokespecial	#161; //Method _Jack2_9:(II)Z
   124:	ifeq	206
   127:	aload_0
   128:	aload_3
   129:	invokevirtual	#294; //Method method_declaration:(Lspec/benchmarks/_228_jack/Container;)V
   132:	aload_0
   133:	bipush	83
   135:	invokespecial	#253; //Method consume_token:(I)V
   138:	aload_3
   139:	getfield	#293; //Field spec/benchmarks/_228_jack/Container.member:Ljava/lang/Object;
   142:	checkcast	#55; //class Production
   145:	astore_2
   146:	aload_0
   147:	bipush	70
   149:	invokespecial	#253; //Method consume_token:(I)V
   152:	aload_0
   153:	aload	4
   155:	invokevirtual	#284; //Method java_declarations_and_code:(Ljava/util/Vector;)V
   158:	aload_0
   159:	bipush	71
   161:	invokespecial	#253; //Method consume_token:(I)V
   164:	aload_0
   165:	aload_2
   166:	aload	4
   168:	invokevirtual	#303; //Method spec/benchmarks/_228_jack/Jack_the_Parser_Generator_Internals.production_adddecls:(Lspec/benchmarks/_228_jack/Production;Ljava/util/Vector;)V
   171:	aload_0
   172:	bipush	70
   174:	invokespecial	#253; //Method consume_token:(I)V
   177:	aload_0
   178:	aload_3
   179:	invokevirtual	#273; //Method expansion_choices:(Lspec/benchmarks/_228_jack/Container;)V
   182:	aload_0
   183:	bipush	71
   185:	invokespecial	#253; //Method consume_token:(I)V
   188:	aload_0
   189:	aload_2
   190:	aload_3
   191:	getfield	#293; //Field spec/benchmarks/_228_jack/Container.member:Ljava/lang/Object;
   194:	checkcast	#43; //class Expansion
   197:	invokevirtual	#304; //Method spec/benchmarks/_228_jack/Jack_the_Parser_Generator_Internals.production_addexpansion:(Lspec/benchmarks/_228_jack/Production;Lspec/benchmarks/_228_jack/Expansion;)V
   200:	aload_0
   201:	aload_2
   202:	invokevirtual	#255; //Method spec/benchmarks/_228_jack/Jack_the_Parser_Generator_Internals.db_addproduction:(Lspec/benchmarks/_228_jack/Production;)V
   205:	return
   206:	aload_0
   207:	ldc	#26; //String production
   209:	invokespecial	#244; //Method choice_error:(Ljava/lang/String;)V
   212:	new	#54; //class ParseError
   215:	dup
   216:	invokespecial	#89; //Method spec/benchmarks/_228_jack/ParseError."<init>":()V
   219:	athrow

public void method_declaration(spec.benchmarks._228_jack.Container);
   throws spec/benchmarks/_228_jack/ParseError
  Code:
   0:	aload_0
   1:	bipush	15
   3:	iconst_1
   4:	invokespecial	#109; //Method _Jack2_10:(II)Z
   7:	ifeq	71
   10:	new	#38; //class BNFProduction
   13:	dup
   14:	invokespecial	#79; //Method spec/benchmarks/_228_jack/BNFProduction."<init>":()V
   17:	astore_3
   18:	aload_1
   19:	aload_3
   20:	putfield	#293; //Field spec/benchmarks/_228_jack/Container.member:Ljava/lang/Object;
   23:	aload_0
   24:	aload_3
   25:	checkcast	#52; //class NormalProduction
   28:	getfield	#310; //Field spec/benchmarks/_228_jack/NormalProduction.return_type_tokens:Ljava/util/Vector;
   31:	invokevirtual	#287; //Method java_return_type:(Ljava/util/Vector;)V
   34:	aload_0
   35:	invokevirtual	#278; //Method identifier:()Ljava/lang/String;
   38:	astore_2
   39:	aload_3
   40:	checkcast	#52; //class NormalProduction
   43:	aload_2
   44:	invokevirtual	#314; //Method spec/benchmarks/_228_jack/NormalProduction.setlhs:(Ljava/lang/String;)V
   47:	aload_0
   48:	bipush	68
   50:	invokespecial	#253; //Method consume_token:(I)V
   53:	aload_0
   54:	aload_3
   55:	checkcast	#52; //class NormalProduction
   58:	getfield	#298; //Field spec/benchmarks/_228_jack/NormalProduction.parameter_list_tokens:Ljava/util/Vector;
   61:	invokevirtual	#286; //Method java_parameter_list:(Ljava/util/Vector;)V
   64:	aload_0
   65:	bipush	69
   67:	invokespecial	#253; //Method consume_token:(I)V
   70:	return
   71:	aload_0
   72:	bipush	15
   74:	iconst_1
   75:	invokespecial	#110; //Method _Jack2_11:(II)Z
   78:	ifeq	101
   81:	aload_0
   82:	bipush	120
   84:	invokespecial	#253; //Method consume_token:(I)V
   87:	new	#45; //class IgnoreInBNFProduction
   90:	dup
   91:	invokespecial	#84; //Method spec/benchmarks/_228_jack/IgnoreInBNFProduction."<init>":()V
   94:	astore_3
   95:	aload_1
   96:	aload_3
   97:	putfield	#293; //Field spec/benchmarks/_228_jack/Container.member:Ljava/lang/Object;
   100:	return
   101:	aload_0
   102:	bipush	15
   104:	iconst_1
   105:	invokespecial	#111; //Method _Jack2_12:(II)Z
   108:	ifeq	131
   111:	aload_0
   112:	bipush	121
   114:	invokespecial	#253; //Method consume_token:(I)V
   117:	new	#71; //class TokenProduction
   120:	dup
   121:	invokespecial	#101; //Method spec/benchmarks/_228_jack/TokenProduction."<init>":()V
   124:	astore_3
   125:	aload_1
   126:	aload_3
   127:	putfield	#293; //Field spec/benchmarks/_228_jack/Container.member:Ljava/lang/Object;
   130:	return
   131:	aload_0
   132:	ldc	#25; //String method_declaration
   134:	invokespecial	#244; //Method choice_error:(Ljava/lang/String;)V
   137:	new	#54; //class ParseError
   140:	dup
   141:	invokespecial	#89; //Method spec/benchmarks/_228_jack/ParseError."<init>":()V
   144:	athrow

public void expansion_choices(spec.benchmarks._228_jack.Container);
   throws spec/benchmarks/_228_jack/ParseError
  Code:
   0:	iconst_0
   1:	istore_2
   2:	aconst_null
   3:	astore_3
   4:	new	#42; //class Container
   7:	dup
   8:	invokespecial	#82; //Method spec/benchmarks/_228_jack/Container."<init>":()V
   11:	astore	4
   13:	aload_0
   14:	aload_1
   15:	invokevirtual	#269; //Method expansion:(Lspec/benchmarks/_228_jack/Container;)V
   18:	goto	85
   21:	aload_0
   22:	bipush	97
   24:	invokespecial	#253; //Method consume_token:(I)V
   27:	aload_0
   28:	aload	4
   30:	invokevirtual	#269; //Method expansion:(Lspec/benchmarks/_228_jack/Container;)V
   33:	iload_2
   34:	ifeq	52
   37:	aload_3
   38:	getfield	#245; //Field spec/benchmarks/_228_jack/Choice.choices:Ljava/util/Vector;
   41:	aload	4
   43:	getfield	#293; //Field spec/benchmarks/_228_jack/Container.member:Ljava/lang/Object;
   46:	invokevirtual	#233; //Method java/util/Vector.addElement:(Ljava/lang/Object;)V
   49:	goto	85
   52:	iconst_1
   53:	istore_2
   54:	new	#41; //class Choice
   57:	dup
   58:	invokespecial	#81; //Method spec/benchmarks/_228_jack/Choice."<init>":()V
   61:	astore_3
   62:	aload_3
   63:	getfield	#245; //Field spec/benchmarks/_228_jack/Choice.choices:Ljava/util/Vector;
   66:	aload_1
   67:	getfield	#293; //Field spec/benchmarks/_228_jack/Container.member:Ljava/lang/Object;
   70:	invokevirtual	#233; //Method java/util/Vector.addElement:(Ljava/lang/Object;)V
   73:	aload_3
   74:	getfield	#245; //Field spec/benchmarks/_228_jack/Choice.choices:Ljava/util/Vector;
   77:	aload	4
   79:	getfield	#293; //Field spec/benchmarks/_228_jack/Container.member:Ljava/lang/Object;
   82:	invokevirtual	#233; //Method java/util/Vector.addElement:(Ljava/lang/Object;)V
   85:	aload_0
   86:	bipush	15
   88:	iconst_1
   89:	invokespecial	#112; //Method _Jack2_13:(II)Z
   92:	ifne	21
   95:	iload_2
   96:	ifeq	104
   99:	aload_1
   100:	aload_3
   101:	putfield	#293; //Field spec/benchmarks/_228_jack/Container.member:Ljava/lang/Object;
   104:	return

public void expansion(spec.benchmarks._228_jack.Container);
   throws spec/benchmarks/_228_jack/ParseError
  Code:
   0:	iconst_0
   1:	istore_2
   2:	aconst_null
   3:	astore_3
   4:	new	#42; //class Container
   7:	dup
   8:	invokespecial	#82; //Method spec/benchmarks/_228_jack/Container."<init>":()V
   11:	astore	4
   13:	aload_0
   14:	aload	4
   16:	invokevirtual	#274; //Method expansion_unit:(Lspec/benchmarks/_228_jack/Container;)V
   19:	iinc	2, 1
   22:	iload_2
   23:	iconst_1
   24:	if_icmpne	39
   27:	aload_1
   28:	aload	4
   30:	getfield	#293; //Field spec/benchmarks/_228_jack/Container.member:Ljava/lang/Object;
   33:	putfield	#293; //Field spec/benchmarks/_228_jack/Container.member:Ljava/lang/Object;
   36:	goto	90
   39:	iload_2
   40:	iconst_2
   41:	if_icmpne	78
   44:	new	#66; //class Sequence
   47:	dup
   48:	invokespecial	#99; //Method spec/benchmarks/_228_jack/Sequence."<init>":()V
   51:	astore_3
   52:	aload_3
   53:	getfield	#324; //Field spec/benchmarks/_228_jack/Sequence.units:Ljava/util/Vector;
   56:	aload_1
   57:	getfield	#293; //Field spec/benchmarks/_228_jack/Container.member:Ljava/lang/Object;
   60:	invokevirtual	#233; //Method java/util/Vector.addElement:(Ljava/lang/Object;)V
   63:	aload_3
   64:	getfield	#324; //Field spec/benchmarks/_228_jack/Sequence.units:Ljava/util/Vector;
   67:	aload	4
   69:	getfield	#293; //Field spec/benchmarks/_228_jack/Container.member:Ljava/lang/Object;
   72:	invokevirtual	#233; //Method java/util/Vector.addElement:(Ljava/lang/Object;)V
   75:	goto	90
   78:	aload_3
   79:	getfield	#324; //Field spec/benchmarks/_228_jack/Sequence.units:Ljava/util/Vector;
   82:	aload	4
   84:	getfield	#293; //Field spec/benchmarks/_228_jack/Container.member:Ljava/lang/Object;
   87:	invokevirtual	#233; //Method java/util/Vector.addElement:(Ljava/lang/Object;)V
   90:	aload_0
   91:	bipush	15
   93:	iconst_1
   94:	invokespecial	#113; //Method _Jack2_14:(II)Z
   97:	ifne	13
   100:	goto	103
   103:	iload_2
   104:	iconst_1
   105:	if_icmple	113
   108:	aload_1
   109:	aload_3
   110:	putfield	#293; //Field spec/benchmarks/_228_jack/Container.member:Ljava/lang/Object;
   113:	return

public void expansion_unit(spec.benchmarks._228_jack.Container);
   throws spec/benchmarks/_228_jack/ParseError
  Code:
   0:	aload_0
   1:	bipush	15
   3:	iconst_1
   4:	invokespecial	#114; //Method _Jack2_15:(II)Z
   7:	ifeq	16
   10:	aload_0
   11:	aload_1
   12:	invokevirtual	#308; //Method regular_expression:(Lspec/benchmarks/_228_jack/Container;)V
   15:	return
   16:	aload_0
   17:	bipush	15
   19:	iconst_1
   20:	invokespecial	#115; //Method _Jack2_16:(II)Z
   23:	ifeq	104
   26:	new	#51; //class NonTerminal
   29:	dup
   30:	invokespecial	#87; //Method spec/benchmarks/_228_jack/NonTerminal."<init>":()V
   33:	astore	4
   35:	ldc	#1; //String 
   37:	astore_2
   38:	aload_0
   39:	bipush	15
   41:	iconst_1
   42:	invokespecial	#116; //Method _Jack2_17:(II)Z
   45:	ifeq	59
   48:	aload_0
   49:	invokevirtual	#278; //Method identifier:()Ljava/lang/String;
   52:	astore_2
   53:	aload_0
   54:	bipush	77
   56:	invokespecial	#253; //Method consume_token:(I)V
   59:	aload_0
   60:	invokevirtual	#278; //Method identifier:()Ljava/lang/String;
   63:	astore_3
   64:	aload_0
   65:	bipush	68
   67:	invokespecial	#253; //Method consume_token:(I)V
   70:	aload_0
   71:	aload	4
   73:	getfield	#236; //Field spec/benchmarks/_228_jack/NonTerminal.argument_tokens:Ljava/util/Vector;
   76:	invokevirtual	#285; //Method java_expression_list:(Ljava/util/Vector;)V
   79:	aload_0
   80:	bipush	69
   82:	invokespecial	#253; //Method consume_token:(I)V
   85:	aload	4
   87:	aload_2
   88:	putfield	#311; //Field spec/benchmarks/_228_jack/NonTerminal.retval:Ljava/lang/String;
   91:	aload	4
   93:	aload_3
   94:	putfield	#295; //Field spec/benchmarks/_228_jack/NonTerminal.name:Ljava/lang/String;
   97:	aload_1
   98:	aload	4
   100:	putfield	#293; //Field spec/benchmarks/_228_jack/Container.member:Ljava/lang/Object;
   103:	return
   104:	aload_0
   105:	bipush	15
   107:	iconst_1
   108:	invokespecial	#117; //Method _Jack2_18:(II)Z
   111:	ifeq	151
   114:	new	#37; //class Action
   117:	dup
   118:	invokespecial	#78; //Method spec/benchmarks/_228_jack/Action."<init>":()V
   121:	astore	5
   123:	aload_0
   124:	bipush	70
   126:	invokespecial	#253; //Method consume_token:(I)V
   129:	aload_0
   130:	aload	5
   132:	getfield	#232; //Field spec/benchmarks/_228_jack/Action.action_tokens:Ljava/util/Vector;
   135:	invokevirtual	#284; //Method java_declarations_and_code:(Ljava/util/Vector;)V
   138:	aload_0
   139:	bipush	71
   141:	invokespecial	#253; //Method consume_token:(I)V
   144:	aload_1
   145:	aload	5
   147:	putfield	#293; //Field spec/benchmarks/_228_jack/Container.member:Ljava/lang/Object;
   150:	return
   151:	aload_0
   152:	bipush	15
   154:	iconst_1
   155:	invokespecial	#118; //Method _Jack2_19:(II)Z
   158:	ifeq	334
   161:	aload_0
   162:	bipush	68
   164:	invokespecial	#253; //Method consume_token:(I)V
   167:	aload_0
   168:	aload_1
   169:	invokevirtual	#273; //Method expansion_choices:(Lspec/benchmarks/_228_jack/Container;)V
   172:	aload_0
   173:	bipush	69
   175:	invokespecial	#253; //Method consume_token:(I)V
   178:	aload_0
   179:	bipush	15
   181:	iconst_1
   182:	invokespecial	#120; //Method _Jack2_20:(II)Z
   185:	ifeq	403
   188:	aload_0
   189:	bipush	15
   191:	iconst_1
   192:	invokespecial	#121; //Method _Jack2_21:(II)Z
   195:	ifeq	232
   198:	aload_0
   199:	bipush	92
   201:	invokespecial	#253; //Method consume_token:(I)V
   204:	new	#53; //class OneOrMore
   207:	dup
   208:	invokespecial	#88; //Method spec/benchmarks/_228_jack/OneOrMore."<init>":()V
   211:	astore	6
   213:	aload	6
   215:	aload_1
   216:	getfield	#293; //Field spec/benchmarks/_228_jack/Container.member:Ljava/lang/Object;
   219:	checkcast	#43; //class Expansion
   222:	putfield	#270; //Field spec/benchmarks/_228_jack/OneOrMore.expansion:Lspec/benchmarks/_228_jack/Expansion;
   225:	aload_1
   226:	aload	6
   228:	putfield	#293; //Field spec/benchmarks/_228_jack/Container.member:Ljava/lang/Object;
   231:	return
   232:	aload_0
   233:	bipush	15
   235:	iconst_1
   236:	invokespecial	#122; //Method _Jack2_22:(II)Z
   239:	ifeq	276
   242:	aload_0
   243:	bipush	94
   245:	invokespecial	#253; //Method consume_token:(I)V
   248:	new	#73; //class ZeroOrMore
   251:	dup
   252:	invokespecial	#103; //Method spec/benchmarks/_228_jack/ZeroOrMore."<init>":()V
   255:	astore	6
   257:	aload	6
   259:	aload_1
   260:	getfield	#293; //Field spec/benchmarks/_228_jack/Container.member:Ljava/lang/Object;
   263:	checkcast	#43; //class Expansion
   266:	putfield	#271; //Field spec/benchmarks/_228_jack/ZeroOrMore.expansion:Lspec/benchmarks/_228_jack/Expansion;
   269:	aload_1
   270:	aload	6
   272:	putfield	#293; //Field spec/benchmarks/_228_jack/Container.member:Ljava/lang/Object;
   275:	return
   276:	aload_0
   277:	bipush	15
   279:	iconst_1
   280:	invokespecial	#123; //Method _Jack2_23:(II)Z
   283:	ifeq	320
   286:	aload_0
   287:	bipush	82
   289:	invokespecial	#253; //Method consume_token:(I)V
   292:	new	#74; //class ZeroOrOne
   295:	dup
   296:	invokespecial	#104; //Method spec/benchmarks/_228_jack/ZeroOrOne."<init>":()V
   299:	astore	6
   301:	aload	6
   303:	aload_1
   304:	getfield	#293; //Field spec/benchmarks/_228_jack/Container.member:Ljava/lang/Object;
   307:	checkcast	#43; //class Expansion
   310:	putfield	#272; //Field spec/benchmarks/_228_jack/ZeroOrOne.expansion:Lspec/benchmarks/_228_jack/Expansion;
   313:	aload_1
   314:	aload	6
   316:	putfield	#293; //Field spec/benchmarks/_228_jack/Container.member:Ljava/lang/Object;
   319:	return
   320:	aload_0
   321:	ldc	#22; //String expansion_unit
   323:	invokespecial	#244; //Method choice_error:(Ljava/lang/String;)V
   326:	new	#54; //class ParseError
   329:	dup
   330:	invokespecial	#89; //Method spec/benchmarks/_228_jack/ParseError."<init>":()V
   333:	athrow
   334:	aload_0
   335:	bipush	15
   337:	iconst_1
   338:	invokespecial	#124; //Method _Jack2_24:(II)Z
   341:	ifeq	389
   344:	aload_0
   345:	bipush	72
   347:	invokespecial	#253; //Method consume_token:(I)V
   350:	aload_0
   351:	aload_1
   352:	invokevirtual	#273; //Method expansion_choices:(Lspec/benchmarks/_228_jack/Container;)V
   355:	aload_0
   356:	bipush	73
   358:	invokespecial	#253; //Method consume_token:(I)V
   361:	new	#74; //class ZeroOrOne
   364:	dup
   365:	invokespecial	#104; //Method spec/benchmarks/_228_jack/ZeroOrOne."<init>":()V
   368:	astore	6
   370:	aload	6
   372:	aload_1
   373:	getfield	#293; //Field spec/benchmarks/_228_jack/Container.member:Ljava/lang/Object;
   376:	checkcast	#43; //class Expansion
   379:	putfield	#272; //Field spec/benchmarks/_228_jack/ZeroOrOne.expansion:Lspec/benchmarks/_228_jack/Expansion;
   382:	aload_1
   383:	aload	6
   385:	putfield	#293; //Field spec/benchmarks/_228_jack/Container.member:Ljava/lang/Object;
   388:	return
   389:	aload_0
   390:	ldc	#22; //String expansion_unit
   392:	invokespecial	#244; //Method choice_error:(Ljava/lang/String;)V
   395:	new	#54; //class ParseError
   398:	dup
   399:	invokespecial	#89; //Method spec/benchmarks/_228_jack/ParseError."<init>":()V
   402:	athrow
   403:	return

void java_declarations_and_code(java.util.Vector);
   throws spec/benchmarks/_228_jack/ParseError
  Code:
   0:	iconst_1
   1:	istore_3
   2:	aload_0
   3:	getfield	#321; //Field token_source:Lspec/benchmarks/_228_jack/TokenManager;
   6:	iconst_1
   7:	invokeinterface	#277,  2; //InterfaceMethod spec/benchmarks/_228_jack/TokenManager.getToken:(I)Lspec/benchmarks/_228_jack/Token;
   12:	astore_2
   13:	aload_2
   14:	getfield	#288; //Field spec/benchmarks/_228_jack/Token.kind:I
   17:	bipush	70
   19:	if_icmpne	25
   22:	iinc	3, 1
   25:	aload_2
   26:	getfield	#288; //Field spec/benchmarks/_228_jack/Token.kind:I
   29:	bipush	71
   31:	if_icmpne	42
   34:	iinc	3, -1
   37:	iload_3
   38:	ifne	42
   41:	return
   42:	aload_0
   43:	getfield	#321; //Field token_source:Lspec/benchmarks/_228_jack/TokenManager;
   46:	invokeinterface	#276,  1; //InterfaceMethod spec/benchmarks/_228_jack/TokenManager.getNextToken:()Lspec/benchmarks/_228_jack/Token;
   51:	astore_2
   52:	aload_1
   53:	aload_2
   54:	invokevirtual	#233; //Method java/util/Vector.addElement:(Ljava/lang/Object;)V
   57:	goto	2
   60:	pop
   61:	new	#54; //class ParseError
   64:	dup
   65:	invokespecial	#89; //Method spec/benchmarks/_228_jack/ParseError."<init>":()V
   68:	athrow
  Exception table:
   from   to  target type
     0    60    60   Class spec/benchmarks/_228_jack/TokenException


public void java_return_type(java.util.Vector);
   throws spec/benchmarks/_228_jack/ParseError
  Code:
   0:	aload_0
   1:	bipush	15
   3:	iconst_1
   4:	invokespecial	#125; //Method _Jack2_25:(II)Z
   7:	ifeq	19
   10:	aload_0
   11:	bipush	60
   13:	invokespecial	#253; //Method consume_token:(I)V
   16:	goto	203
   19:	aload_0
   20:	bipush	15
   22:	iconst_1
   23:	invokespecial	#126; //Method _Jack2_26:(II)Z
   26:	ifeq	38
   29:	aload_0
   30:	bipush	10
   32:	invokespecial	#253; //Method consume_token:(I)V
   35:	goto	203
   38:	aload_0
   39:	bipush	15
   41:	iconst_1
   42:	invokespecial	#127; //Method _Jack2_27:(II)Z
   45:	ifeq	57
   48:	aload_0
   49:	bipush	49
   51:	invokespecial	#253; //Method consume_token:(I)V
   54:	goto	203
   57:	aload_0
   58:	bipush	15
   60:	iconst_1
   61:	invokespecial	#128; //Method _Jack2_28:(II)Z
   64:	ifeq	76
   67:	aload_0
   68:	bipush	35
   70:	invokespecial	#253; //Method consume_token:(I)V
   73:	goto	203
   76:	aload_0
   77:	bipush	15
   79:	iconst_1
   80:	invokespecial	#129; //Method _Jack2_29:(II)Z
   83:	ifeq	95
   86:	aload_0
   87:	bipush	37
   89:	invokespecial	#253; //Method consume_token:(I)V
   92:	goto	203
   95:	aload_0
   96:	bipush	15
   98:	iconst_1
   99:	invokespecial	#131; //Method _Jack2_30:(II)Z
   102:	ifeq	114
   105:	aload_0
   106:	bipush	25
   108:	invokespecial	#253; //Method consume_token:(I)V
   111:	goto	203
   114:	aload_0
   115:	bipush	15
   117:	iconst_1
   118:	invokespecial	#132; //Method _Jack2_31:(II)Z
   121:	ifeq	133
   124:	aload_0
   125:	bipush	20
   127:	invokespecial	#253; //Method consume_token:(I)V
   130:	goto	203
   133:	aload_0
   134:	bipush	15
   136:	iconst_1
   137:	invokespecial	#133; //Method _Jack2_32:(II)Z
   140:	ifeq	152
   143:	aload_0
   144:	bipush	14
   146:	invokespecial	#253; //Method consume_token:(I)V
   149:	goto	203
   152:	aload_0
   153:	bipush	15
   155:	iconst_1
   156:	invokespecial	#134; //Method _Jack2_33:(II)Z
   159:	ifeq	171
   162:	aload_0
   163:	bipush	8
   165:	invokespecial	#253; //Method consume_token:(I)V
   168:	goto	203
   171:	aload_0
   172:	bipush	15
   174:	iconst_1
   175:	invokespecial	#135; //Method _Jack2_34:(II)Z
   178:	ifeq	189
   181:	aload_0
   182:	invokevirtual	#278; //Method identifier:()Ljava/lang/String;
   185:	astore_2
   186:	goto	203
   189:	aload_0
   190:	ldc	#24; //String java_return_type
   192:	invokespecial	#244; //Method choice_error:(Ljava/lang/String;)V
   195:	new	#54; //class ParseError
   198:	dup
   199:	invokespecial	#89; //Method spec/benchmarks/_228_jack/ParseError."<init>":()V
   202:	athrow
   203:	aload_1
   204:	aload_0
   205:	getfield	#318; //Field token:Lspec/benchmarks/_228_jack/Token;
   208:	invokevirtual	#233; //Method java/util/Vector.addElement:(Ljava/lang/Object;)V
   211:	goto	242
   214:	aload_0
   215:	bipush	72
   217:	invokespecial	#253; //Method consume_token:(I)V
   220:	aload_1
   221:	aload_0
   222:	getfield	#318; //Field token:Lspec/benchmarks/_228_jack/Token;
   225:	invokevirtual	#233; //Method java/util/Vector.addElement:(Ljava/lang/Object;)V
   228:	aload_0
   229:	bipush	73
   231:	invokespecial	#253; //Method consume_token:(I)V
   234:	aload_1
   235:	aload_0
   236:	getfield	#318; //Field token:Lspec/benchmarks/_228_jack/Token;
   239:	invokevirtual	#233; //Method java/util/Vector.addElement:(Ljava/lang/Object;)V
   242:	aload_0
   243:	bipush	15
   245:	iconst_1
   246:	invokespecial	#136; //Method _Jack2_35:(II)Z
   249:	ifne	214
   252:	return

void java_parameter_list(java.util.Vector);
   throws spec/benchmarks/_228_jack/ParseError
  Code:
   0:	iconst_1
   1:	istore_3
   2:	aload_0
   3:	getfield	#321; //Field token_source:Lspec/benchmarks/_228_jack/TokenManager;
   6:	iconst_1
   7:	invokeinterface	#277,  2; //InterfaceMethod spec/benchmarks/_228_jack/TokenManager.getToken:(I)Lspec/benchmarks/_228_jack/Token;
   12:	astore_2
   13:	aload_2
   14:	getfield	#288; //Field spec/benchmarks/_228_jack/Token.kind:I
   17:	bipush	68
   19:	if_icmpne	25
   22:	iinc	3, 1
   25:	aload_2
   26:	getfield	#288; //Field spec/benchmarks/_228_jack/Token.kind:I
   29:	bipush	69
   31:	if_icmpne	42
   34:	iinc	3, -1
   37:	iload_3
   38:	ifne	42
   41:	return
   42:	aload_0
   43:	getfield	#321; //Field token_source:Lspec/benchmarks/_228_jack/TokenManager;
   46:	invokeinterface	#276,  1; //InterfaceMethod spec/benchmarks/_228_jack/TokenManager.getNextToken:()Lspec/benchmarks/_228_jack/Token;
   51:	astore_2
   52:	aload_1
   53:	aload_2
   54:	invokevirtual	#233; //Method java/util/Vector.addElement:(Ljava/lang/Object;)V
   57:	goto	2
   60:	pop
   61:	new	#54; //class ParseError
   64:	dup
   65:	invokespecial	#89; //Method spec/benchmarks/_228_jack/ParseError."<init>":()V
   68:	athrow
  Exception table:
   from   to  target type
     0    60    60   Class spec/benchmarks/_228_jack/TokenException


void java_expression_list(java.util.Vector);
   throws spec/benchmarks/_228_jack/ParseError
  Code:
   0:	iconst_1
   1:	istore_3
   2:	aload_0
   3:	getfield	#321; //Field token_source:Lspec/benchmarks/_228_jack/TokenManager;
   6:	iconst_1
   7:	invokeinterface	#277,  2; //InterfaceMethod spec/benchmarks/_228_jack/TokenManager.getToken:(I)Lspec/benchmarks/_228_jack/Token;
   12:	astore_2
   13:	aload_2
   14:	getfield	#288; //Field spec/benchmarks/_228_jack/Token.kind:I
   17:	bipush	68
   19:	if_icmpne	25
   22:	iinc	3, 1
   25:	aload_2
   26:	getfield	#288; //Field spec/benchmarks/_228_jack/Token.kind:I
   29:	bipush	69
   31:	if_icmpne	42
   34:	iinc	3, -1
   37:	iload_3
   38:	ifne	42
   41:	return
   42:	aload_0
   43:	getfield	#321; //Field token_source:Lspec/benchmarks/_228_jack/TokenManager;
   46:	invokeinterface	#276,  1; //InterfaceMethod spec/benchmarks/_228_jack/TokenManager.getNextToken:()Lspec/benchmarks/_228_jack/Token;
   51:	astore_2
   52:	aload_1
   53:	aload_2
   54:	invokevirtual	#233; //Method java/util/Vector.addElement:(Ljava/lang/Object;)V
   57:	goto	2
   60:	pop
   61:	new	#54; //class ParseError
   64:	dup
   65:	invokespecial	#89; //Method spec/benchmarks/_228_jack/ParseError."<init>":()V
   68:	athrow
  Exception table:
   from   to  target type
     0    60    60   Class spec/benchmarks/_228_jack/TokenException


public void regular_expression(spec.benchmarks._228_jack.Container);
   throws spec/benchmarks/_228_jack/ParseError
  Code:
   0:	aload_0
   1:	bipush	15
   3:	iconst_1
   4:	invokespecial	#137; //Method _Jack2_36:(II)Z
   7:	ifeq	36
   10:	aload_0
   11:	invokevirtual	#316; //Method string_literal:()Ljava/lang/String;
   14:	astore	4
   16:	new	#62; //class RStringLiteral
   19:	dup
   20:	invokespecial	#96; //Method spec/benchmarks/_228_jack/RStringLiteral."<init>":()V
   23:	astore_2
   24:	aload_2
   25:	aload	4
   27:	putfield	#279; //Field spec/benchmarks/_228_jack/RStringLiteral.image:Ljava/lang/String;
   30:	aload_1
   31:	aload_2
   32:	putfield	#293; //Field spec/benchmarks/_228_jack/Container.member:Ljava/lang/Object;
   35:	return
   36:	aload_0
   37:	bipush	15
   39:	iconst_1
   40:	invokespecial	#138; //Method _Jack2_37:(II)Z
   43:	ifeq	102
   46:	ldc	#1; //String 
   48:	astore	4
   50:	aload_0
   51:	bipush	79
   53:	invokespecial	#253; //Method consume_token:(I)V
   56:	aload_0
   57:	bipush	15
   59:	iconst_1
   60:	invokespecial	#139; //Method _Jack2_38:(II)Z
   63:	ifeq	78
   66:	aload_0
   67:	invokevirtual	#278; //Method identifier:()Ljava/lang/String;
   70:	astore	4
   72:	aload_0
   73:	bipush	83
   75:	invokespecial	#253; //Method consume_token:(I)V
   78:	aload_0
   79:	aload_1
   80:	invokevirtual	#250; //Method complex_regular_expression_choices:(Lspec/benchmarks/_228_jack/Container;)V
   83:	aload_0
   84:	bipush	78
   86:	invokespecial	#253; //Method consume_token:(I)V
   89:	aload_1
   90:	getfield	#293; //Field spec/benchmarks/_228_jack/Container.member:Ljava/lang/Object;
   93:	checkcast	#65; //class RegularExpression
   96:	aload	4
   98:	putfield	#291; //Field spec/benchmarks/_228_jack/RegularExpression.label:Ljava/lang/String;
   101:	return
   102:	aload_0
   103:	bipush	15
   105:	iconst_1
   106:	invokespecial	#140; //Method _Jack2_39:(II)Z
   109:	ifeq	150
   112:	aload_0
   113:	bipush	79
   115:	invokespecial	#253; //Method consume_token:(I)V
   118:	aload_0
   119:	invokevirtual	#278; //Method identifier:()Ljava/lang/String;
   122:	astore	4
   124:	aload_0
   125:	bipush	78
   127:	invokespecial	#253; //Method consume_token:(I)V
   130:	new	#59; //class RJustName
   133:	dup
   134:	invokespecial	#93; //Method spec/benchmarks/_228_jack/RJustName."<init>":()V
   137:	astore_3
   138:	aload_3
   139:	aload	4
   141:	putfield	#291; //Field spec/benchmarks/_228_jack/RegularExpression.label:Ljava/lang/String;
   144:	aload_1
   145:	aload_3
   146:	putfield	#293; //Field spec/benchmarks/_228_jack/Container.member:Ljava/lang/Object;
   149:	return
   150:	aload_0
   151:	bipush	15
   153:	iconst_1
   154:	invokespecial	#142; //Method _Jack2_40:(II)Z
   157:	ifeq	190
   160:	aload_0
   161:	bipush	79
   163:	invokespecial	#253; //Method consume_token:(I)V
   166:	aload_0
   167:	bipush	122
   169:	invokespecial	#253; //Method consume_token:(I)V
   172:	aload_0
   173:	bipush	78
   175:	invokespecial	#253; //Method consume_token:(I)V
   178:	aload_1
   179:	new	#58; //class REndOfFile
   182:	dup
   183:	invokespecial	#92; //Method spec/benchmarks/_228_jack/REndOfFile."<init>":()V
   186:	putfield	#293; //Field spec/benchmarks/_228_jack/Container.member:Ljava/lang/Object;
   189:	return
   190:	aload_0
   191:	ldc	#27; //String regular_expression
   193:	invokespecial	#244; //Method choice_error:(Ljava/lang/String;)V
   196:	new	#54; //class ParseError
   199:	dup
   200:	invokespecial	#89; //Method spec/benchmarks/_228_jack/ParseError."<init>":()V
   203:	athrow

public java.lang.String string_literal();
   throws spec/benchmarks/_228_jack/ParseError
  Code:
   0:	aload_0
   1:	bipush	66
   3:	invokespecial	#253; //Method consume_token:(I)V
   6:	aload_0
   7:	aload_0
   8:	getfield	#321; //Field token_source:Lspec/benchmarks/_228_jack/TokenManager;
   11:	iconst_0
   12:	invokeinterface	#277,  2; //InterfaceMethod spec/benchmarks/_228_jack/TokenManager.getToken:(I)Lspec/benchmarks/_228_jack/Token;
   17:	getfield	#280; //Field spec/benchmarks/_228_jack/Token.image:Ljava/lang/String;
   20:	invokevirtual	#309; //Method spec/benchmarks/_228_jack/Jack_the_Parser_Generator_Internals.remove_escapes_and_quotes:(Ljava/lang/String;)Ljava/lang/String;
   23:	areturn
   24:	pop
   25:	new	#29; //class Error
   28:	dup
   29:	invokespecial	#76; //Method java/lang/Error."<init>":()V
   32:	athrow
  Exception table:
   from   to  target type
     6    24    24   Class spec/benchmarks/_228_jack/TokenException


public void complex_regular_expression_choices(spec.benchmarks._228_jack.Container);
   throws spec/benchmarks/_228_jack/ParseError
  Code:
   0:	iconst_0
   1:	istore_2
   2:	aconst_null
   3:	astore_3
   4:	new	#42; //class Container
   7:	dup
   8:	invokespecial	#82; //Method spec/benchmarks/_228_jack/Container."<init>":()V
   11:	astore	4
   13:	aload_0
   14:	aload_1
   15:	invokevirtual	#249; //Method complex_regular_expression:(Lspec/benchmarks/_228_jack/Container;)V
   18:	goto	85
   21:	aload_0
   22:	bipush	97
   24:	invokespecial	#253; //Method consume_token:(I)V
   27:	aload_0
   28:	aload	4
   30:	invokevirtual	#249; //Method complex_regular_expression:(Lspec/benchmarks/_228_jack/Container;)V
   33:	iload_2
   34:	ifeq	52
   37:	aload_3
   38:	getfield	#246; //Field spec/benchmarks/_228_jack/RChoice.choices:Ljava/util/Vector;
   41:	aload	4
   43:	getfield	#293; //Field spec/benchmarks/_228_jack/Container.member:Ljava/lang/Object;
   46:	invokevirtual	#233; //Method java/util/Vector.addElement:(Ljava/lang/Object;)V
   49:	goto	85
   52:	iconst_1
   53:	istore_2
   54:	new	#57; //class RChoice
   57:	dup
   58:	invokespecial	#91; //Method spec/benchmarks/_228_jack/RChoice."<init>":()V
   61:	astore_3
   62:	aload_3
   63:	getfield	#246; //Field spec/benchmarks/_228_jack/RChoice.choices:Ljava/util/Vector;
   66:	aload_1
   67:	getfield	#293; //Field spec/benchmarks/_228_jack/Container.member:Ljava/lang/Object;
   70:	invokevirtual	#233; //Method java/util/Vector.addElement:(Ljava/lang/Object;)V
   73:	aload_3
   74:	getfield	#246; //Field spec/benchmarks/_228_jack/RChoice.choices:Ljava/util/Vector;
   77:	aload	4
   79:	getfield	#293; //Field spec/benchmarks/_228_jack/Container.member:Ljava/lang/Object;
   82:	invokevirtual	#233; //Method java/util/Vector.addElement:(Ljava/lang/Object;)V
   85:	aload_0
   86:	bipush	15
   88:	iconst_1
   89:	invokespecial	#143; //Method _Jack2_41:(II)Z
   92:	ifne	21
   95:	iload_2
   96:	ifeq	104
   99:	aload_1
   100:	aload_3
   101:	putfield	#293; //Field spec/benchmarks/_228_jack/Container.member:Ljava/lang/Object;
   104:	return

public void complex_regular_expression(spec.benchmarks._228_jack.Container);
   throws spec/benchmarks/_228_jack/ParseError
  Code:
   0:	iconst_0
   1:	istore_2
   2:	aconst_null
   3:	astore_3
   4:	new	#42; //class Container
   7:	dup
   8:	invokespecial	#82; //Method spec/benchmarks/_228_jack/Container."<init>":()V
   11:	astore	4
   13:	aload_0
   14:	aload	4
   16:	invokevirtual	#251; //Method complex_regular_expression_unit:(Lspec/benchmarks/_228_jack/Container;)V
   19:	iinc	2, 1
   22:	iload_2
   23:	iconst_1
   24:	if_icmpne	39
   27:	aload_1
   28:	aload	4
   30:	getfield	#293; //Field spec/benchmarks/_228_jack/Container.member:Ljava/lang/Object;
   33:	putfield	#293; //Field spec/benchmarks/_228_jack/Container.member:Ljava/lang/Object;
   36:	goto	90
   39:	iload_2
   40:	iconst_2
   41:	if_icmpne	78
   44:	new	#61; //class RSequence
   47:	dup
   48:	invokespecial	#95; //Method spec/benchmarks/_228_jack/RSequence."<init>":()V
   51:	astore_3
   52:	aload_3
   53:	getfield	#323; //Field spec/benchmarks/_228_jack/RSequence.units:Ljava/util/Vector;
   56:	aload_1
   57:	getfield	#293; //Field spec/benchmarks/_228_jack/Container.member:Ljava/lang/Object;
   60:	invokevirtual	#233; //Method java/util/Vector.addElement:(Ljava/lang/Object;)V
   63:	aload_3
   64:	getfield	#323; //Field spec/benchmarks/_228_jack/RSequence.units:Ljava/util/Vector;
   67:	aload	4
   69:	getfield	#293; //Field spec/benchmarks/_228_jack/Container.member:Ljava/lang/Object;
   72:	invokevirtual	#233; //Method java/util/Vector.addElement:(Ljava/lang/Object;)V
   75:	goto	90
   78:	aload_3
   79:	getfield	#323; //Field spec/benchmarks/_228_jack/RSequence.units:Ljava/util/Vector;
   82:	aload	4
   84:	getfield	#293; //Field spec/benchmarks/_228_jack/Container.member:Ljava/lang/Object;
   87:	invokevirtual	#233; //Method java/util/Vector.addElement:(Ljava/lang/Object;)V
   90:	aload_0
   91:	bipush	15
   93:	iconst_1
   94:	invokespecial	#144; //Method _Jack2_42:(II)Z
   97:	ifne	13
   100:	goto	103
   103:	iload_2
   104:	iconst_1
   105:	if_icmple	113
   108:	aload_1
   109:	aload_3
   110:	putfield	#293; //Field spec/benchmarks/_228_jack/Container.member:Ljava/lang/Object;
   113:	return

public void complex_regular_expression_unit(spec.benchmarks._228_jack.Container);
   throws spec/benchmarks/_228_jack/ParseError
  Code:
   0:	aload_0
   1:	bipush	15
   3:	iconst_1
   4:	invokespecial	#145; //Method _Jack2_43:(II)Z
   7:	ifeq	34
   10:	aload_0
   11:	invokevirtual	#316; //Method string_literal:()Ljava/lang/String;
   14:	astore_2
   15:	new	#62; //class RStringLiteral
   18:	dup
   19:	invokespecial	#96; //Method spec/benchmarks/_228_jack/RStringLiteral."<init>":()V
   22:	astore_3
   23:	aload_3
   24:	aload_2
   25:	putfield	#279; //Field spec/benchmarks/_228_jack/RStringLiteral.image:Ljava/lang/String;
   28:	aload_1
   29:	aload_3
   30:	putfield	#293; //Field spec/benchmarks/_228_jack/Container.member:Ljava/lang/Object;
   33:	return
   34:	aload_0
   35:	bipush	15
   37:	iconst_1
   38:	invokespecial	#146; //Method _Jack2_44:(II)Z
   41:	ifeq	83
   44:	aload_0
   45:	bipush	79
   47:	invokespecial	#253; //Method consume_token:(I)V
   50:	aload_0
   51:	invokevirtual	#278; //Method identifier:()Ljava/lang/String;
   54:	astore_2
   55:	aload_0
   56:	bipush	78
   58:	invokespecial	#253; //Method consume_token:(I)V
   61:	new	#59; //class RJustName
   64:	dup
   65:	invokespecial	#93; //Method spec/benchmarks/_228_jack/RJustName."<init>":()V
   68:	astore	4
   70:	aload	4
   72:	aload_2
   73:	putfield	#291; //Field spec/benchmarks/_228_jack/RegularExpression.label:Ljava/lang/String;
   76:	aload_1
   77:	aload	4
   79:	putfield	#293; //Field spec/benchmarks/_228_jack/Container.member:Ljava/lang/Object;
   82:	return
   83:	aload_0
   84:	bipush	15
   86:	iconst_1
   87:	invokespecial	#147; //Method _Jack2_45:(II)Z
   90:	ifeq	99
   93:	aload_0
   94:	aload_1
   95:	invokevirtual	#243; //Method character_list:(Lspec/benchmarks/_228_jack/Container;)V
   98:	return
   99:	aload_0
   100:	bipush	15
   102:	iconst_1
   103:	invokespecial	#148; //Method _Jack2_46:(II)Z
   106:	ifeq	282
   109:	aload_0
   110:	bipush	68
   112:	invokespecial	#253; //Method consume_token:(I)V
   115:	aload_0
   116:	aload_1
   117:	invokevirtual	#250; //Method complex_regular_expression_choices:(Lspec/benchmarks/_228_jack/Container;)V
   120:	aload_0
   121:	bipush	69
   123:	invokespecial	#253; //Method consume_token:(I)V
   126:	aload_0
   127:	bipush	15
   129:	iconst_1
   130:	invokespecial	#149; //Method _Jack2_47:(II)Z
   133:	ifeq	296
   136:	aload_0
   137:	bipush	15
   139:	iconst_1
   140:	invokespecial	#150; //Method _Jack2_48:(II)Z
   143:	ifeq	180
   146:	aload_0
   147:	bipush	92
   149:	invokespecial	#253; //Method consume_token:(I)V
   152:	new	#60; //class ROneOrMore
   155:	dup
   156:	invokespecial	#94; //Method spec/benchmarks/_228_jack/ROneOrMore."<init>":()V
   159:	astore	5
   161:	aload	5
   163:	aload_1
   164:	getfield	#293; //Field spec/benchmarks/_228_jack/Container.member:Ljava/lang/Object;
   167:	checkcast	#65; //class RegularExpression
   170:	putfield	#305; //Field spec/benchmarks/_228_jack/ROneOrMore.regexpr:Lspec/benchmarks/_228_jack/RegularExpression;
   173:	aload_1
   174:	aload	5
   176:	putfield	#293; //Field spec/benchmarks/_228_jack/Container.member:Ljava/lang/Object;
   179:	return
   180:	aload_0
   181:	bipush	15
   183:	iconst_1
   184:	invokespecial	#151; //Method _Jack2_49:(II)Z
   187:	ifeq	224
   190:	aload_0
   191:	bipush	94
   193:	invokespecial	#253; //Method consume_token:(I)V
   196:	new	#63; //class RZeroOrMore
   199:	dup
   200:	invokespecial	#97; //Method spec/benchmarks/_228_jack/RZeroOrMore."<init>":()V
   203:	astore	5
   205:	aload	5
   207:	aload_1
   208:	getfield	#293; //Field spec/benchmarks/_228_jack/Container.member:Ljava/lang/Object;
   211:	checkcast	#65; //class RegularExpression
   214:	putfield	#306; //Field spec/benchmarks/_228_jack/RZeroOrMore.regexpr:Lspec/benchmarks/_228_jack/RegularExpression;
   217:	aload_1
   218:	aload	5
   220:	putfield	#293; //Field spec/benchmarks/_228_jack/Container.member:Ljava/lang/Object;
   223:	return
   224:	aload_0
   225:	bipush	15
   227:	iconst_1
   228:	invokespecial	#153; //Method _Jack2_50:(II)Z
   231:	ifeq	268
   234:	aload_0
   235:	bipush	82
   237:	invokespecial	#253; //Method consume_token:(I)V
   240:	new	#64; //class RZeroOrOne
   243:	dup
   244:	invokespecial	#98; //Method spec/benchmarks/_228_jack/RZeroOrOne."<init>":()V
   247:	astore	5
   249:	aload	5
   251:	aload_1
   252:	getfield	#293; //Field spec/benchmarks/_228_jack/Container.member:Ljava/lang/Object;
   255:	checkcast	#65; //class RegularExpression
   258:	putfield	#307; //Field spec/benchmarks/_228_jack/RZeroOrOne.regexpr:Lspec/benchmarks/_228_jack/RegularExpression;
   261:	aload_1
   262:	aload	5
   264:	putfield	#293; //Field spec/benchmarks/_228_jack/Container.member:Ljava/lang/Object;
   267:	return
   268:	aload_0
   269:	ldc	#21; //String complex_regular_expression_unit
   271:	invokespecial	#244; //Method choice_error:(Ljava/lang/String;)V
   274:	new	#54; //class ParseError
   277:	dup
   278:	invokespecial	#89; //Method spec/benchmarks/_228_jack/ParseError."<init>":()V
   281:	athrow
   282:	aload_0
   283:	ldc	#21; //String complex_regular_expression_unit
   285:	invokespecial	#244; //Method choice_error:(Ljava/lang/String;)V
   288:	new	#54; //class ParseError
   291:	dup
   292:	invokespecial	#89; //Method spec/benchmarks/_228_jack/ParseError."<init>":()V
   295:	athrow
   296:	return

public void character_list(spec.benchmarks._228_jack.Container);
   throws spec/benchmarks/_228_jack/ParseError
  Code:
   0:	new	#56; //class RCharacterList
   3:	dup
   4:	invokespecial	#90; //Method spec/benchmarks/_228_jack/RCharacterList."<init>":()V
   7:	astore_2
   8:	new	#42; //class Container
   11:	dup
   12:	invokespecial	#82; //Method spec/benchmarks/_228_jack/Container."<init>":()V
   15:	astore_3
   16:	aload_0
   17:	bipush	15
   19:	iconst_1
   20:	invokespecial	#154; //Method _Jack2_51:(II)Z
   23:	ifeq	37
   26:	aload_0
   27:	bipush	81
   29:	invokespecial	#253; //Method consume_token:(I)V
   32:	aload_2
   33:	iconst_1
   34:	putfield	#296; //Field spec/benchmarks/_228_jack/RCharacterList.negated_list:Z
   37:	aload_0
   38:	bipush	72
   40:	invokespecial	#253; //Method consume_token:(I)V
   43:	aload_0
   44:	bipush	15
   46:	iconst_1
   47:	invokespecial	#155; //Method _Jack2_52:(II)Z
   50:	ifeq	104
   53:	aload_0
   54:	aload_3
   55:	invokevirtual	#241; //Method character_descriptor:(Lspec/benchmarks/_228_jack/Container;)V
   58:	aload_2
   59:	getfield	#261; //Field spec/benchmarks/_228_jack/RCharacterList.descriptors:Ljava/util/Vector;
   62:	aload_3
   63:	getfield	#293; //Field spec/benchmarks/_228_jack/Container.member:Ljava/lang/Object;
   66:	invokevirtual	#233; //Method java/util/Vector.addElement:(Ljava/lang/Object;)V
   69:	goto	94
   72:	aload_0
   73:	bipush	75
   75:	invokespecial	#253; //Method consume_token:(I)V
   78:	aload_0
   79:	aload_3
   80:	invokevirtual	#241; //Method character_descriptor:(Lspec/benchmarks/_228_jack/Container;)V
   83:	aload_2
   84:	getfield	#261; //Field spec/benchmarks/_228_jack/RCharacterList.descriptors:Ljava/util/Vector;
   87:	aload_3
   88:	getfield	#293; //Field spec/benchmarks/_228_jack/Container.member:Ljava/lang/Object;
   91:	invokevirtual	#233; //Method java/util/Vector.addElement:(Ljava/lang/Object;)V
   94:	aload_0
   95:	bipush	15
   97:	iconst_1
   98:	invokespecial	#156; //Method _Jack2_53:(II)Z
   101:	ifne	72
   104:	aload_0
   105:	bipush	73
   107:	invokespecial	#253; //Method consume_token:(I)V
   110:	aload_1
   111:	aload_2
   112:	putfield	#293; //Field spec/benchmarks/_228_jack/Container.member:Ljava/lang/Object;
   115:	return

public void character_descriptor(spec.benchmarks._228_jack.Container);
   throws spec/benchmarks/_228_jack/ParseError
  Code:
   0:	bipush	32
   2:	istore_3
   3:	iconst_0
   4:	istore	4
   6:	aload_0
   7:	invokevirtual	#316; //Method string_literal:()Ljava/lang/String;
   10:	astore	5
   12:	aload_0
   13:	aload	5
   15:	invokevirtual	#242; //Method spec/benchmarks/_228_jack/Jack_the_Parser_Generator_Internals.character_descriptor_assign:(Ljava/lang/String;)C
   18:	istore_2
   19:	aload_0
   20:	bipush	15
   22:	iconst_1
   23:	invokespecial	#157; //Method _Jack2_54:(II)Z
   26:	ifeq	51
   29:	aload_0
   30:	bipush	93
   32:	invokespecial	#253; //Method consume_token:(I)V
   35:	aload_0
   36:	invokevirtual	#316; //Method string_literal:()Ljava/lang/String;
   39:	astore	5
   41:	iconst_1
   42:	istore	4
   44:	aload_0
   45:	aload	5
   47:	invokevirtual	#242; //Method spec/benchmarks/_228_jack/Jack_the_Parser_Generator_Internals.character_descriptor_assign:(Ljava/lang/String;)C
   50:	istore_3
   51:	iload	4
   53:	ifeq	84
   56:	new	#40; //class CharacterRange
   59:	dup
   60:	invokespecial	#80; //Method spec/benchmarks/_228_jack/CharacterRange."<init>":()V
   63:	astore	6
   65:	aload	6
   67:	iload_2
   68:	putfield	#292; //Field spec/benchmarks/_228_jack/CharacterRange.left:C
   71:	aload	6
   73:	iload_3
   74:	putfield	#312; //Field spec/benchmarks/_228_jack/CharacterRange.right:C
   77:	aload_1
   78:	aload	6
   80:	putfield	#293; //Field spec/benchmarks/_228_jack/Container.member:Ljava/lang/Object;
   83:	return
   84:	new	#67; //class SingleCharacter
   87:	dup
   88:	invokespecial	#100; //Method spec/benchmarks/_228_jack/SingleCharacter."<init>":()V
   91:	astore	6
   93:	aload	6
   95:	iload_2
   96:	putfield	#240; //Field spec/benchmarks/_228_jack/SingleCharacter.ch:C
   99:	aload_1
   100:	aload	6
   102:	putfield	#293; //Field spec/benchmarks/_228_jack/Container.member:Ljava/lang/Object;
   105:	return

public java.lang.String identifier();
   throws spec/benchmarks/_228_jack/ParseError
  Code:
   0:	aload_0
   1:	bipush	123
   3:	invokespecial	#253; //Method consume_token:(I)V
   6:	aload_0
   7:	getfield	#321; //Field token_source:Lspec/benchmarks/_228_jack/TokenManager;
   10:	iconst_0
   11:	invokeinterface	#277,  2; //InterfaceMethod spec/benchmarks/_228_jack/TokenManager.getToken:(I)Lspec/benchmarks/_228_jack/Token;
   16:	getfield	#280; //Field spec/benchmarks/_228_jack/Token.image:Ljava/lang/String;
   19:	areturn
   20:	pop
   21:	new	#29; //class Error
   24:	dup
   25:	invokespecial	#76; //Method java/lang/Error."<init>":()V
   28:	athrow
  Exception table:
   from   to  target type
     6    20    20   Class spec/benchmarks/_228_jack/TokenException


private boolean _Jack2_1(int,int);
  Code:
   0:	aload_0
   1:	iload_1
   2:	putfield	#289; //Field la:I
   5:	aload_0
   6:	iload_2
   7:	putfield	#281; //Field index:I
   10:	aload_0
   11:	invokespecial	#162; //Method _Jack3_1:()V
   14:	goto	23
   17:	pop
   18:	iconst_1
   19:	ireturn
   20:	pop
   21:	iconst_0
   22:	ireturn
   23:	iconst_1
   24:	ireturn
  Exception table:
   from   to  target type
    10    14    17   Class spec/benchmarks/_228_jack/TrueException

    10    14    20   Class spec/benchmarks/_228_jack/FalseException


private boolean _Jack2_2(int,int);
  Code:
   0:	aload_0
   1:	iload_1
   2:	putfield	#289; //Field la:I
   5:	aload_0
   6:	iload_2
   7:	putfield	#281; //Field index:I
   10:	aload_0
   11:	invokespecial	#173; //Method _Jack3_2:()V
   14:	goto	23
   17:	pop
   18:	iconst_1
   19:	ireturn
   20:	pop
   21:	iconst_0
   22:	ireturn
   23:	iconst_1
   24:	ireturn
  Exception table:
   from   to  target type
    10    14    17   Class spec/benchmarks/_228_jack/TrueException

    10    14    20   Class spec/benchmarks/_228_jack/FalseException


private boolean _Jack2_3(int,int);
  Code:
   0:	aload_0
   1:	iload_1
   2:	putfield	#289; //Field la:I
   5:	aload_0
   6:	iload_2
   7:	putfield	#281; //Field index:I
   10:	aload_0
   11:	invokespecial	#184; //Method _Jack3_3:()V
   14:	goto	23
   17:	pop
   18:	iconst_1
   19:	ireturn
   20:	pop
   21:	iconst_0
   22:	ireturn
   23:	iconst_1
   24:	ireturn
  Exception table:
   from   to  target type
    10    14    17   Class spec/benchmarks/_228_jack/TrueException

    10    14    20   Class spec/benchmarks/_228_jack/FalseException


private boolean _Jack2_4(int,int);
  Code:
   0:	aload_0
   1:	iload_1
   2:	putfield	#289; //Field la:I
   5:	aload_0
   6:	iload_2
   7:	putfield	#281; //Field index:I
   10:	aload_0
   11:	invokespecial	#195; //Method _Jack3_4:()V
   14:	goto	23
   17:	pop
   18:	iconst_1
   19:	ireturn
   20:	pop
   21:	iconst_0
   22:	ireturn
   23:	iconst_1
   24:	ireturn
  Exception table:
   from   to  target type
    10    14    17   Class spec/benchmarks/_228_jack/TrueException

    10    14    20   Class spec/benchmarks/_228_jack/FalseException


private boolean _Jack2_5(int,int);
  Code:
   0:	aload_0
   1:	iload_1
   2:	putfield	#289; //Field la:I
   5:	aload_0
   6:	iload_2
   7:	putfield	#281; //Field index:I
   10:	aload_0
   11:	invokespecial	#206; //Method _Jack3_5:()V
   14:	goto	23
   17:	pop
   18:	iconst_1
   19:	ireturn
   20:	pop
   21:	iconst_0
   22:	ireturn
   23:	iconst_1
   24:	ireturn
  Exception table:
   from   to  target type
    10    14    17   Class spec/benchmarks/_228_jack/TrueException

    10    14    20   Class spec/benchmarks/_228_jack/FalseException


private boolean _Jack2_6(int,int);
  Code:
   0:	aload_0
   1:	iload_1
   2:	putfield	#289; //Field la:I
   5:	aload_0
   6:	iload_2
   7:	putfield	#281; //Field index:I
   10:	aload_0
   11:	invokespecial	#212; //Method _Jack3_6:()V
   14:	goto	23
   17:	pop
   18:	iconst_1
   19:	ireturn
   20:	pop
   21:	iconst_0
   22:	ireturn
   23:	iconst_1
   24:	ireturn
  Exception table:
   from   to  target type
    10    14    17   Class spec/benchmarks/_228_jack/TrueException

    10    14    20   Class spec/benchmarks/_228_jack/FalseException


private boolean _Jack2_7(int,int);
  Code:
   0:	aload_0
   1:	iload_1
   2:	putfield	#289; //Field la:I
   5:	aload_0
   6:	iload_2
   7:	putfield	#281; //Field index:I
   10:	aload_0
   11:	invokespecial	#213; //Method _Jack3_7:()V
   14:	goto	23
   17:	pop
   18:	iconst_1
   19:	ireturn
   20:	pop
   21:	iconst_0
   22:	ireturn
   23:	iconst_1
   24:	ireturn
  Exception table:
   from   to  target type
    10    14    17   Class spec/benchmarks/_228_jack/TrueException

    10    14    20   Class spec/benchmarks/_228_jack/FalseException


private boolean _Jack2_8(int,int);
  Code:
   0:	aload_0
   1:	iload_1
   2:	putfield	#289; //Field la:I
   5:	aload_0
   6:	iload_2
   7:	putfield	#281; //Field index:I
   10:	aload_0
   11:	invokespecial	#214; //Method _Jack3_8:()V
   14:	goto	23
   17:	pop
   18:	iconst_1
   19:	ireturn
   20:	pop
   21:	iconst_0
   22:	ireturn
   23:	iconst_1
   24:	ireturn
  Exception table:
   from   to  target type
    10    14    17   Class spec/benchmarks/_228_jack/TrueException

    10    14    20   Class spec/benchmarks/_228_jack/FalseException


private boolean _Jack2_9(int,int);
  Code:
   0:	aload_0
   1:	iload_1
   2:	putfield	#289; //Field la:I
   5:	aload_0
   6:	iload_2
   7:	putfield	#281; //Field index:I
   10:	aload_0
   11:	invokespecial	#215; //Method _Jack3_9:()V
   14:	goto	23
   17:	pop
   18:	iconst_1
   19:	ireturn
   20:	pop
   21:	iconst_0
   22:	ireturn
   23:	iconst_1
   24:	ireturn
  Exception table:
   from   to  target type
    10    14    17   Class spec/benchmarks/_228_jack/TrueException

    10    14    20   Class spec/benchmarks/_228_jack/FalseException


private boolean _Jack2_10(int,int);
  Code:
   0:	aload_0
   1:	iload_1
   2:	putfield	#289; //Field la:I
   5:	aload_0
   6:	iload_2
   7:	putfield	#281; //Field index:I
   10:	aload_0
   11:	invokespecial	#163; //Method _Jack3_10:()V
   14:	goto	23
   17:	pop
   18:	iconst_1
   19:	ireturn
   20:	pop
   21:	iconst_0
   22:	ireturn
   23:	iconst_1
   24:	ireturn
  Exception table:
   from   to  target type
    10    14    17   Class spec/benchmarks/_228_jack/TrueException

    10    14    20   Class spec/benchmarks/_228_jack/FalseException


private boolean _Jack2_11(int,int);
  Code:
   0:	aload_0
   1:	iload_1
   2:	putfield	#289; //Field la:I
   5:	aload_0
   6:	iload_2
   7:	putfield	#281; //Field index:I
   10:	aload_0
   11:	invokespecial	#164; //Method _Jack3_11:()V
   14:	goto	23
   17:	pop
   18:	iconst_1
   19:	ireturn
   20:	pop
   21:	iconst_0
   22:	ireturn
   23:	iconst_1
   24:	ireturn
  Exception table:
   from   to  target type
    10    14    17   Class spec/benchmarks/_228_jack/TrueException

    10    14    20   Class spec/benchmarks/_228_jack/FalseException


private boolean _Jack2_12(int,int);
  Code:
   0:	aload_0
   1:	iload_1
   2:	putfield	#289; //Field la:I
   5:	aload_0
   6:	iload_2
   7:	putfield	#281; //Field index:I
   10:	aload_0
   11:	invokespecial	#165; //Method _Jack3_12:()V
   14:	goto	23
   17:	pop
   18:	iconst_1
   19:	ireturn
   20:	pop
   21:	iconst_0
   22:	ireturn
   23:	iconst_1
   24:	ireturn
  Exception table:
   from   to  target type
    10    14    17   Class spec/benchmarks/_228_jack/TrueException

    10    14    20   Class spec/benchmarks/_228_jack/FalseException


private boolean _Jack2_13(int,int);
  Code:
   0:	aload_0
   1:	iload_1
   2:	putfield	#289; //Field la:I
   5:	aload_0
   6:	iload_2
   7:	putfield	#281; //Field index:I
   10:	aload_0
   11:	invokespecial	#166; //Method _Jack3_13:()V
   14:	goto	23
   17:	pop
   18:	iconst_1
   19:	ireturn
   20:	pop
   21:	iconst_0
   22:	ireturn
   23:	iconst_1
   24:	ireturn
  Exception table:
   from   to  target type
    10    14    17   Class spec/benchmarks/_228_jack/TrueException

    10    14    20   Class spec/benchmarks/_228_jack/FalseException


private boolean _Jack2_14(int,int);
  Code:
   0:	aload_0
   1:	iload_1
   2:	putfield	#289; //Field la:I
   5:	aload_0
   6:	iload_2
   7:	putfield	#281; //Field index:I
   10:	aload_0
   11:	invokespecial	#167; //Method _Jack3_14:()V
   14:	goto	23
   17:	pop
   18:	iconst_1
   19:	ireturn
   20:	pop
   21:	iconst_0
   22:	ireturn
   23:	iconst_1
   24:	ireturn
  Exception table:
   from   to  target type
    10    14    17   Class spec/benchmarks/_228_jack/TrueException

    10    14    20   Class spec/benchmarks/_228_jack/FalseException


private boolean _Jack2_15(int,int);
  Code:
   0:	aload_0
   1:	iload_1
   2:	putfield	#289; //Field la:I
   5:	aload_0
   6:	iload_2
   7:	putfield	#281; //Field index:I
   10:	aload_0
   11:	invokespecial	#168; //Method _Jack3_15:()V
   14:	goto	23
   17:	pop
   18:	iconst_1
   19:	ireturn
   20:	pop
   21:	iconst_0
   22:	ireturn
   23:	iconst_1
   24:	ireturn
  Exception table:
   from   to  target type
    10    14    17   Class spec/benchmarks/_228_jack/TrueException

    10    14    20   Class spec/benchmarks/_228_jack/FalseException


private boolean _Jack2_16(int,int);
  Code:
   0:	aload_0
   1:	iload_1
   2:	putfield	#289; //Field la:I
   5:	aload_0
   6:	iload_2
   7:	putfield	#281; //Field index:I
   10:	aload_0
   11:	invokespecial	#169; //Method _Jack3_16:()V
   14:	goto	23
   17:	pop
   18:	iconst_1
   19:	ireturn
   20:	pop
   21:	iconst_0
   22:	ireturn
   23:	iconst_1
   24:	ireturn
  Exception table:
   from   to  target type
    10    14    17   Class spec/benchmarks/_228_jack/TrueException

    10    14    20   Class spec/benchmarks/_228_jack/FalseException


private boolean _Jack2_17(int,int);
  Code:
   0:	aload_0
   1:	iload_1
   2:	putfield	#289; //Field la:I
   5:	aload_0
   6:	iload_2
   7:	putfield	#281; //Field index:I
   10:	aload_0
   11:	invokespecial	#170; //Method _Jack3_17:()V
   14:	goto	23
   17:	pop
   18:	iconst_1
   19:	ireturn
   20:	pop
   21:	iconst_0
   22:	ireturn
   23:	iconst_1
   24:	ireturn
  Exception table:
   from   to  target type
    10    14    17   Class spec/benchmarks/_228_jack/TrueException

    10    14    20   Class spec/benchmarks/_228_jack/FalseException


private boolean _Jack2_18(int,int);
  Code:
   0:	aload_0
   1:	iload_1
   2:	putfield	#289; //Field la:I
   5:	aload_0
   6:	iload_2
   7:	putfield	#281; //Field index:I
   10:	aload_0
   11:	invokespecial	#171; //Method _Jack3_18:()V
   14:	goto	23
   17:	pop
   18:	iconst_1
   19:	ireturn
   20:	pop
   21:	iconst_0
   22:	ireturn
   23:	iconst_1
   24:	ireturn
  Exception table:
   from   to  target type
    10    14    17   Class spec/benchmarks/_228_jack/TrueException

    10    14    20   Class spec/benchmarks/_228_jack/FalseException


private boolean _Jack2_19(int,int);
  Code:
   0:	aload_0
   1:	iload_1
   2:	putfield	#289; //Field la:I
   5:	aload_0
   6:	iload_2
   7:	putfield	#281; //Field index:I
   10:	aload_0
   11:	invokespecial	#172; //Method _Jack3_19:()V
   14:	goto	23
   17:	pop
   18:	iconst_1
   19:	ireturn
   20:	pop
   21:	iconst_0
   22:	ireturn
   23:	iconst_1
   24:	ireturn
  Exception table:
   from   to  target type
    10    14    17   Class spec/benchmarks/_228_jack/TrueException

    10    14    20   Class spec/benchmarks/_228_jack/FalseException


private boolean _Jack2_20(int,int);
  Code:
   0:	aload_0
   1:	iload_1
   2:	putfield	#289; //Field la:I
   5:	aload_0
   6:	iload_2
   7:	putfield	#281; //Field index:I
   10:	aload_0
   11:	invokespecial	#174; //Method _Jack3_20:()V
   14:	goto	23
   17:	pop
   18:	iconst_1
   19:	ireturn
   20:	pop
   21:	iconst_0
   22:	ireturn
   23:	iconst_1
   24:	ireturn
  Exception table:
   from   to  target type
    10    14    17   Class spec/benchmarks/_228_jack/TrueException

    10    14    20   Class spec/benchmarks/_228_jack/FalseException


private boolean _Jack2_21(int,int);
  Code:
   0:	aload_0
   1:	iload_1
   2:	putfield	#289; //Field la:I
   5:	aload_0
   6:	iload_2
   7:	putfield	#281; //Field index:I
   10:	aload_0
   11:	invokespecial	#175; //Method _Jack3_21:()V
   14:	goto	23
   17:	pop
   18:	iconst_1
   19:	ireturn
   20:	pop
   21:	iconst_0
   22:	ireturn
   23:	iconst_1
   24:	ireturn
  Exception table:
   from   to  target type
    10    14    17   Class spec/benchmarks/_228_jack/TrueException

    10    14    20   Class spec/benchmarks/_228_jack/FalseException


private boolean _Jack2_22(int,int);
  Code:
   0:	aload_0
   1:	iload_1
   2:	putfield	#289; //Field la:I
   5:	aload_0
   6:	iload_2
   7:	putfield	#281; //Field index:I
   10:	aload_0
   11:	invokespecial	#176; //Method _Jack3_22:()V
   14:	goto	23
   17:	pop
   18:	iconst_1
   19:	ireturn
   20:	pop
   21:	iconst_0
   22:	ireturn
   23:	iconst_1
   24:	ireturn
  Exception table:
   from   to  target type
    10    14    17   Class spec/benchmarks/_228_jack/TrueException

    10    14    20   Class spec/benchmarks/_228_jack/FalseException


private boolean _Jack2_23(int,int);
  Code:
   0:	aload_0
   1:	iload_1
   2:	putfield	#289; //Field la:I
   5:	aload_0
   6:	iload_2
   7:	putfield	#281; //Field index:I
   10:	aload_0
   11:	invokespecial	#177; //Method _Jack3_23:()V
   14:	goto	23
   17:	pop
   18:	iconst_1
   19:	ireturn
   20:	pop
   21:	iconst_0
   22:	ireturn
   23:	iconst_1
   24:	ireturn
  Exception table:
   from   to  target type
    10    14    17   Class spec/benchmarks/_228_jack/TrueException

    10    14    20   Class spec/benchmarks/_228_jack/FalseException


private boolean _Jack2_24(int,int);
  Code:
   0:	aload_0
   1:	iload_1
   2:	putfield	#289; //Field la:I
   5:	aload_0
   6:	iload_2
   7:	putfield	#281; //Field index:I
   10:	aload_0
   11:	invokespecial	#178; //Method _Jack3_24:()V
   14:	goto	23
   17:	pop
   18:	iconst_1
   19:	ireturn
   20:	pop
   21:	iconst_0
   22:	ireturn
   23:	iconst_1
   24:	ireturn
  Exception table:
   from   to  target type
    10    14    17   Class spec/benchmarks/_228_jack/TrueException

    10    14    20   Class spec/benchmarks/_228_jack/FalseException


private boolean _Jack2_25(int,int);
  Code:
   0:	aload_0
   1:	iload_1
   2:	putfield	#289; //Field la:I
   5:	aload_0
   6:	iload_2
   7:	putfield	#281; //Field index:I
   10:	aload_0
   11:	invokespecial	#179; //Method _Jack3_25:()V
   14:	goto	23
   17:	pop
   18:	iconst_1
   19:	ireturn
   20:	pop
   21:	iconst_0
   22:	ireturn
   23:	iconst_1
   24:	ireturn
  Exception table:
   from   to  target type
    10    14    17   Class spec/benchmarks/_228_jack/TrueException

    10    14    20   Class spec/benchmarks/_228_jack/FalseException


private boolean _Jack2_26(int,int);
  Code:
   0:	aload_0
   1:	iload_1
   2:	putfield	#289; //Field la:I
   5:	aload_0
   6:	iload_2
   7:	putfield	#281; //Field index:I
   10:	aload_0
   11:	invokespecial	#180; //Method _Jack3_26:()V
   14:	goto	23
   17:	pop
   18:	iconst_1
   19:	ireturn
   20:	pop
   21:	iconst_0
   22:	ireturn
   23:	iconst_1
   24:	ireturn
  Exception table:
   from   to  target type
    10    14    17   Class spec/benchmarks/_228_jack/TrueException

    10    14    20   Class spec/benchmarks/_228_jack/FalseException


private boolean _Jack2_27(int,int);
  Code:
   0:	aload_0
   1:	iload_1
   2:	putfield	#289; //Field la:I
   5:	aload_0
   6:	iload_2
   7:	putfield	#281; //Field index:I
   10:	aload_0
   11:	invokespecial	#181; //Method _Jack3_27:()V
   14:	goto	23
   17:	pop
   18:	iconst_1
   19:	ireturn
   20:	pop
   21:	iconst_0
   22:	ireturn
   23:	iconst_1
   24:	ireturn
  Exception table:
   from   to  target type
    10    14    17   Class spec/benchmarks/_228_jack/TrueException

    10    14    20   Class spec/benchmarks/_228_jack/FalseException


private boolean _Jack2_28(int,int);
  Code:
   0:	aload_0
   1:	iload_1
   2:	putfield	#289; //Field la:I
   5:	aload_0
   6:	iload_2
   7:	putfield	#281; //Field index:I
   10:	aload_0
   11:	invokespecial	#182; //Method _Jack3_28:()V
   14:	goto	23
   17:	pop
   18:	iconst_1
   19:	ireturn
   20:	pop
   21:	iconst_0
   22:	ireturn
   23:	iconst_1
   24:	ireturn
  Exception table:
   from   to  target type
    10    14    17   Class spec/benchmarks/_228_jack/TrueException

    10    14    20   Class spec/benchmarks/_228_jack/FalseException


private boolean _Jack2_29(int,int);
  Code:
   0:	aload_0
   1:	iload_1
   2:	putfield	#289; //Field la:I
   5:	aload_0
   6:	iload_2
   7:	putfield	#281; //Field index:I
   10:	aload_0
   11:	invokespecial	#183; //Method _Jack3_29:()V
   14:	goto	23
   17:	pop
   18:	iconst_1
   19:	ireturn
   20:	pop
   21:	iconst_0
   22:	ireturn
   23:	iconst_1
   24:	ireturn
  Exception table:
   from   to  target type
    10    14    17   Class spec/benchmarks/_228_jack/TrueException

    10    14    20   Class spec/benchmarks/_228_jack/FalseException


private boolean _Jack2_30(int,int);
  Code:
   0:	aload_0
   1:	iload_1
   2:	putfield	#289; //Field la:I
   5:	aload_0
   6:	iload_2
   7:	putfield	#281; //Field index:I
   10:	aload_0
   11:	invokespecial	#185; //Method _Jack3_30:()V
   14:	goto	23
   17:	pop
   18:	iconst_1
   19:	ireturn
   20:	pop
   21:	iconst_0
   22:	ireturn
   23:	iconst_1
   24:	ireturn
  Exception table:
   from   to  target type
    10    14    17   Class spec/benchmarks/_228_jack/TrueException

    10    14    20   Class spec/benchmarks/_228_jack/FalseException


private boolean _Jack2_31(int,int);
  Code:
   0:	aload_0
   1:	iload_1
   2:	putfield	#289; //Field la:I
   5:	aload_0
   6:	iload_2
   7:	putfield	#281; //Field index:I
   10:	aload_0
   11:	invokespecial	#186; //Method _Jack3_31:()V
   14:	goto	23
   17:	pop
   18:	iconst_1
   19:	ireturn
   20:	pop
   21:	iconst_0
   22:	ireturn
   23:	iconst_1
   24:	ireturn
  Exception table:
   from   to  target type
    10    14    17   Class spec/benchmarks/_228_jack/TrueException

    10    14    20   Class spec/benchmarks/_228_jack/FalseException


private boolean _Jack2_32(int,int);
  Code:
   0:	aload_0
   1:	iload_1
   2:	putfield	#289; //Field la:I
   5:	aload_0
   6:	iload_2
   7:	putfield	#281; //Field index:I
   10:	aload_0
   11:	invokespecial	#187; //Method _Jack3_32:()V
   14:	goto	23
   17:	pop
   18:	iconst_1
   19:	ireturn
   20:	pop
   21:	iconst_0
   22:	ireturn
   23:	iconst_1
   24:	ireturn
  Exception table:
   from   to  target type
    10    14    17   Class spec/benchmarks/_228_jack/TrueException

    10    14    20   Class spec/benchmarks/_228_jack/FalseException


private boolean _Jack2_33(int,int);
  Code:
   0:	aload_0
   1:	iload_1
   2:	putfield	#289; //Field la:I
   5:	aload_0
   6:	iload_2
   7:	putfield	#281; //Field index:I
   10:	aload_0
   11:	invokespecial	#188; //Method _Jack3_33:()V
   14:	goto	23
   17:	pop
   18:	iconst_1
   19:	ireturn
   20:	pop
   21:	iconst_0
   22:	ireturn
   23:	iconst_1
   24:	ireturn
  Exception table:
   from   to  target type
    10    14    17   Class spec/benchmarks/_228_jack/TrueException

    10    14    20   Class spec/benchmarks/_228_jack/FalseException


private boolean _Jack2_34(int,int);
  Code:
   0:	aload_0
   1:	iload_1
   2:	putfield	#289; //Field la:I
   5:	aload_0
   6:	iload_2
   7:	putfield	#281; //Field index:I
   10:	aload_0
   11:	invokespecial	#189; //Method _Jack3_34:()V
   14:	goto	23
   17:	pop
   18:	iconst_1
   19:	ireturn
   20:	pop
   21:	iconst_0
   22:	ireturn
   23:	iconst_1
   24:	ireturn
  Exception table:
   from   to  target type
    10    14    17   Class spec/benchmarks/_228_jack/TrueException

    10    14    20   Class spec/benchmarks/_228_jack/FalseException


private boolean _Jack2_35(int,int);
  Code:
   0:	aload_0
   1:	iload_1
   2:	putfield	#289; //Field la:I
   5:	aload_0
   6:	iload_2
   7:	putfield	#281; //Field index:I
   10:	aload_0
   11:	invokespecial	#190; //Method _Jack3_35:()V
   14:	goto	23
   17:	pop
   18:	iconst_1
   19:	ireturn
   20:	pop
   21:	iconst_0
   22:	ireturn
   23:	iconst_1
   24:	ireturn
  Exception table:
   from   to  target type
    10    14    17   Class spec/benchmarks/_228_jack/TrueException

    10    14    20   Class spec/benchmarks/_228_jack/FalseException


private boolean _Jack2_36(int,int);
  Code:
   0:	aload_0
   1:	iload_1
   2:	putfield	#289; //Field la:I
   5:	aload_0
   6:	iload_2
   7:	putfield	#281; //Field index:I
   10:	aload_0
   11:	invokespecial	#191; //Method _Jack3_36:()V
   14:	goto	23
   17:	pop
   18:	iconst_1
   19:	ireturn
   20:	pop
   21:	iconst_0
   22:	ireturn
   23:	iconst_1
   24:	ireturn
  Exception table:
   from   to  target type
    10    14    17   Class spec/benchmarks/_228_jack/TrueException

    10    14    20   Class spec/benchmarks/_228_jack/FalseException


private boolean _Jack2_37(int,int);
  Code:
   0:	aload_0
   1:	iload_1
   2:	putfield	#289; //Field la:I
   5:	aload_0
   6:	iload_2
   7:	putfield	#281; //Field index:I
   10:	aload_0
   11:	invokespecial	#192; //Method _Jack3_37:()V
   14:	goto	23
   17:	pop
   18:	iconst_1
   19:	ireturn
   20:	pop
   21:	iconst_0
   22:	ireturn
   23:	iconst_1
   24:	ireturn
  Exception table:
   from   to  target type
    10    14    17   Class spec/benchmarks/_228_jack/TrueException

    10    14    20   Class spec/benchmarks/_228_jack/FalseException


private boolean _Jack2_38(int,int);
  Code:
   0:	aload_0
   1:	iload_1
   2:	putfield	#289; //Field la:I
   5:	aload_0
   6:	iload_2
   7:	putfield	#281; //Field index:I
   10:	aload_0
   11:	invokespecial	#193; //Method _Jack3_38:()V
   14:	goto	23
   17:	pop
   18:	iconst_1
   19:	ireturn
   20:	pop
   21:	iconst_0
   22:	ireturn
   23:	iconst_1
   24:	ireturn
  Exception table:
   from   to  target type
    10    14    17   Class spec/benchmarks/_228_jack/TrueException

    10    14    20   Class spec/benchmarks/_228_jack/FalseException


private boolean _Jack2_39(int,int);
  Code:
   0:	aload_0
   1:	iload_1
   2:	putfield	#289; //Field la:I
   5:	aload_0
   6:	iload_2
   7:	putfield	#281; //Field index:I
   10:	aload_0
   11:	invokespecial	#194; //Method _Jack3_39:()V
   14:	goto	23
   17:	pop
   18:	iconst_1
   19:	ireturn
   20:	pop
   21:	iconst_0
   22:	ireturn
   23:	iconst_1
   24:	ireturn
  Exception table:
   from   to  target type
    10    14    17   Class spec/benchmarks/_228_jack/TrueException

    10    14    20   Class spec/benchmarks/_228_jack/FalseException


private boolean _Jack2_40(int,int);
  Code:
   0:	aload_0
   1:	iload_1
   2:	putfield	#289; //Field la:I
   5:	aload_0
   6:	iload_2
   7:	putfield	#281; //Field index:I
   10:	aload_0
   11:	invokespecial	#196; //Method _Jack3_40:()V
   14:	goto	23
   17:	pop
   18:	iconst_1
   19:	ireturn
   20:	pop
   21:	iconst_0
   22:	ireturn
   23:	iconst_1
   24:	ireturn
  Exception table:
   from   to  target type
    10    14    17   Class spec/benchmarks/_228_jack/TrueException

    10    14    20   Class spec/benchmarks/_228_jack/FalseException


private boolean _Jack2_41(int,int);
  Code:
   0:	aload_0
   1:	iload_1
   2:	putfield	#289; //Field la:I
   5:	aload_0
   6:	iload_2
   7:	putfield	#281; //Field index:I
   10:	aload_0
   11:	invokespecial	#197; //Method _Jack3_41:()V
   14:	goto	23
   17:	pop
   18:	iconst_1
   19:	ireturn
   20:	pop
   21:	iconst_0
   22:	ireturn
   23:	iconst_1
   24:	ireturn
  Exception table:
   from   to  target type
    10    14    17   Class spec/benchmarks/_228_jack/TrueException

    10    14    20   Class spec/benchmarks/_228_jack/FalseException


private boolean _Jack2_42(int,int);
  Code:
   0:	aload_0
   1:	iload_1
   2:	putfield	#289; //Field la:I
   5:	aload_0
   6:	iload_2
   7:	putfield	#281; //Field index:I
   10:	aload_0
   11:	invokespecial	#198; //Method _Jack3_42:()V
   14:	goto	23
   17:	pop
   18:	iconst_1
   19:	ireturn
   20:	pop
   21:	iconst_0
   22:	ireturn
   23:	iconst_1
   24:	ireturn
  Exception table:
   from   to  target type
    10    14    17   Class spec/benchmarks/_228_jack/TrueException

    10    14    20   Class spec/benchmarks/_228_jack/FalseException


private boolean _Jack2_43(int,int);
  Code:
   0:	aload_0
   1:	iload_1
   2:	putfield	#289; //Field la:I
   5:	aload_0
   6:	iload_2
   7:	putfield	#281; //Field index:I
   10:	aload_0
   11:	invokespecial	#199; //Method _Jack3_43:()V
   14:	goto	23
   17:	pop
   18:	iconst_1
   19:	ireturn
   20:	pop
   21:	iconst_0
   22:	ireturn
   23:	iconst_1
   24:	ireturn
  Exception table:
   from   to  target type
    10    14    17   Class spec/benchmarks/_228_jack/TrueException

    10    14    20   Class spec/benchmarks/_228_jack/FalseException


private boolean _Jack2_44(int,int);
  Code:
   0:	aload_0
   1:	iload_1
   2:	putfield	#289; //Field la:I
   5:	aload_0
   6:	iload_2
   7:	putfield	#281; //Field index:I
   10:	aload_0
   11:	invokespecial	#200; //Method _Jack3_44:()V
   14:	goto	23
   17:	pop
   18:	iconst_1
   19:	ireturn
   20:	pop
   21:	iconst_0
   22:	ireturn
   23:	iconst_1
   24:	ireturn
  Exception table:
   from   to  target type
    10    14    17   Class spec/benchmarks/_228_jack/TrueException

    10    14    20   Class spec/benchmarks/_228_jack/FalseException


private boolean _Jack2_45(int,int);
  Code:
   0:	aload_0
   1:	iload_1
   2:	putfield	#289; //Field la:I
   5:	aload_0
   6:	iload_2
   7:	putfield	#281; //Field index:I
   10:	aload_0
   11:	invokespecial	#201; //Method _Jack3_45:()V
   14:	goto	23
   17:	pop
   18:	iconst_1
   19:	ireturn
   20:	pop
   21:	iconst_0
   22:	ireturn
   23:	iconst_1
   24:	ireturn
  Exception table:
   from   to  target type
    10    14    17   Class spec/benchmarks/_228_jack/TrueException

    10    14    20   Class spec/benchmarks/_228_jack/FalseException


private boolean _Jack2_46(int,int);
  Code:
   0:	aload_0
   1:	iload_1
   2:	putfield	#289; //Field la:I
   5:	aload_0
   6:	iload_2
   7:	putfield	#281; //Field index:I
   10:	aload_0
   11:	invokespecial	#202; //Method _Jack3_46:()V
   14:	goto	23
   17:	pop
   18:	iconst_1
   19:	ireturn
   20:	pop
   21:	iconst_0
   22:	ireturn
   23:	iconst_1
   24:	ireturn
  Exception table:
   from   to  target type
    10    14    17   Class spec/benchmarks/_228_jack/TrueException

    10    14    20   Class spec/benchmarks/_228_jack/FalseException


private boolean _Jack2_47(int,int);
  Code:
   0:	aload_0
   1:	iload_1
   2:	putfield	#289; //Field la:I
   5:	aload_0
   6:	iload_2
   7:	putfield	#281; //Field index:I
   10:	aload_0
   11:	invokespecial	#203; //Method _Jack3_47:()V
   14:	goto	23
   17:	pop
   18:	iconst_1
   19:	ireturn
   20:	pop
   21:	iconst_0
   22:	ireturn
   23:	iconst_1
   24:	ireturn
  Exception table:
   from   to  target type
    10    14    17   Class spec/benchmarks/_228_jack/TrueException

    10    14    20   Class spec/benchmarks/_228_jack/FalseException


private boolean _Jack2_48(int,int);
  Code:
   0:	aload_0
   1:	iload_1
   2:	putfield	#289; //Field la:I
   5:	aload_0
   6:	iload_2
   7:	putfield	#281; //Field index:I
   10:	aload_0
   11:	invokespecial	#204; //Method _Jack3_48:()V
   14:	goto	23
   17:	pop
   18:	iconst_1
   19:	ireturn
   20:	pop
   21:	iconst_0
   22:	ireturn
   23:	iconst_1
   24:	ireturn
  Exception table:
   from   to  target type
    10    14    17   Class spec/benchmarks/_228_jack/TrueException

    10    14    20   Class spec/benchmarks/_228_jack/FalseException


private boolean _Jack2_49(int,int);
  Code:
   0:	aload_0
   1:	iload_1
   2:	putfield	#289; //Field la:I
   5:	aload_0
   6:	iload_2
   7:	putfield	#281; //Field index:I
   10:	aload_0
   11:	invokespecial	#205; //Method _Jack3_49:()V
   14:	goto	23
   17:	pop
   18:	iconst_1
   19:	ireturn
   20:	pop
   21:	iconst_0
   22:	ireturn
   23:	iconst_1
   24:	ireturn
  Exception table:
   from   to  target type
    10    14    17   Class spec/benchmarks/_228_jack/TrueException

    10    14    20   Class spec/benchmarks/_228_jack/FalseException


private boolean _Jack2_50(int,int);
  Code:
   0:	aload_0
   1:	iload_1
   2:	putfield	#289; //Field la:I
   5:	aload_0
   6:	iload_2
   7:	putfield	#281; //Field index:I
   10:	aload_0
   11:	invokespecial	#207; //Method _Jack3_50:()V
   14:	goto	23
   17:	pop
   18:	iconst_1
   19:	ireturn
   20:	pop
   21:	iconst_0
   22:	ireturn
   23:	iconst_1
   24:	ireturn
  Exception table:
   from   to  target type
    10    14    17   Class spec/benchmarks/_228_jack/TrueException

    10    14    20   Class spec/benchmarks/_228_jack/FalseException


private boolean _Jack2_51(int,int);
  Code:
   0:	aload_0
   1:	iload_1
   2:	putfield	#289; //Field la:I
   5:	aload_0
   6:	iload_2
   7:	putfield	#281; //Field index:I
   10:	aload_0
   11:	invokespecial	#208; //Method _Jack3_51:()V
   14:	goto	23
   17:	pop
   18:	iconst_1
   19:	ireturn
   20:	pop
   21:	iconst_0
   22:	ireturn
   23:	iconst_1
   24:	ireturn
  Exception table:
   from   to  target type
    10    14    17   Class spec/benchmarks/_228_jack/TrueException

    10    14    20   Class spec/benchmarks/_228_jack/FalseException


private boolean _Jack2_52(int,int);
  Code:
   0:	aload_0
   1:	iload_1
   2:	putfield	#289; //Field la:I
   5:	aload_0
   6:	iload_2
   7:	putfield	#281; //Field index:I
   10:	aload_0
   11:	invokespecial	#209; //Method _Jack3_52:()V
   14:	goto	23
   17:	pop
   18:	iconst_1
   19:	ireturn
   20:	pop
   21:	iconst_0
   22:	ireturn
   23:	iconst_1
   24:	ireturn
  Exception table:
   from   to  target type
    10    14    17   Class spec/benchmarks/_228_jack/TrueException

    10    14    20   Class spec/benchmarks/_228_jack/FalseException


private boolean _Jack2_53(int,int);
  Code:
   0:	aload_0
   1:	iload_1
   2:	putfield	#289; //Field la:I
   5:	aload_0
   6:	iload_2
   7:	putfield	#281; //Field index:I
   10:	aload_0
   11:	invokespecial	#210; //Method _Jack3_53:()V
   14:	goto	23
   17:	pop
   18:	iconst_1
   19:	ireturn
   20:	pop
   21:	iconst_0
   22:	ireturn
   23:	iconst_1
   24:	ireturn
  Exception table:
   from   to  target type
    10    14    17   Class spec/benchmarks/_228_jack/TrueException

    10    14    20   Class spec/benchmarks/_228_jack/FalseException


private boolean _Jack2_54(int,int);
  Code:
   0:	aload_0
   1:	iload_1
   2:	putfield	#289; //Field la:I
   5:	aload_0
   6:	iload_2
   7:	putfield	#281; //Field index:I
   10:	aload_0
   11:	invokespecial	#211; //Method _Jack3_54:()V
   14:	goto	23
   17:	pop
   18:	iconst_1
   19:	ireturn
   20:	pop
   21:	iconst_0
   22:	ireturn
   23:	iconst_1
   24:	ireturn
  Exception table:
   from   to  target type
    10    14    17   Class spec/benchmarks/_228_jack/TrueException

    10    14    20   Class spec/benchmarks/_228_jack/FalseException


private void _Jack3_1();
   throws spec/benchmarks/_228_jack/TrueException, spec/benchmarks/_228_jack/FalseException
  Code:
   0:	aload_0
   1:	getfield	#289; //Field la:I
   4:	istore_1
   5:	aload_0
   6:	getfield	#281; //Field index:I
   9:	istore_2
   10:	aload_0
   11:	aload_0
   12:	iload_1
   13:	iconst_3
   14:	if_icmple	21
   17:	iconst_3
   18:	goto	22
   21:	iload_1
   22:	iload_2
   23:	invokespecial	#119; //Method _Jack2_2:(II)Z
   26:	putfield	#252; //Field cond:Z
   29:	aload_0
   30:	iload_1
   31:	putfield	#289; //Field la:I
   34:	aload_0
   35:	iload_2
   36:	putfield	#281; //Field index:I
   39:	aload_0
   40:	getfield	#252; //Field cond:Z
   43:	ifeq	51
   46:	aload_0
   47:	invokespecial	#173; //Method _Jack3_2:()V
   50:	return
   51:	aload_0
   52:	getfield	#289; //Field la:I
   55:	istore_1
   56:	aload_0
   57:	getfield	#281; //Field index:I
   60:	istore_2
   61:	aload_0
   62:	aload_0
   63:	iload_1
   64:	iconst_3
   65:	if_icmple	72
   68:	iconst_3
   69:	goto	73
   72:	iload_1
   73:	iload_2
   74:	invokespecial	#130; //Method _Jack2_3:(II)Z
   77:	putfield	#252; //Field cond:Z
   80:	aload_0
   81:	iload_1
   82:	putfield	#289; //Field la:I
   85:	aload_0
   86:	iload_2
   87:	putfield	#281; //Field index:I
   90:	aload_0
   91:	getfield	#252; //Field cond:Z
   94:	ifeq	102
   97:	aload_0
   98:	invokespecial	#184; //Method _Jack3_3:()V
   101:	return
   102:	aload_0
   103:	getfield	#289; //Field la:I
   106:	istore_1
   107:	aload_0
   108:	getfield	#281; //Field index:I
   111:	istore_2
   112:	aload_0
   113:	aload_0
   114:	iload_1
   115:	iconst_3
   116:	if_icmple	123
   119:	iconst_3
   120:	goto	124
   123:	iload_1
   124:	iload_2
   125:	invokespecial	#141; //Method _Jack2_4:(II)Z
   128:	putfield	#252; //Field cond:Z
   131:	aload_0
   132:	iload_1
   133:	putfield	#289; //Field la:I
   136:	aload_0
   137:	iload_2
   138:	putfield	#281; //Field index:I
   141:	aload_0
   142:	getfield	#252; //Field cond:Z
   145:	ifeq	153
   148:	aload_0
   149:	invokespecial	#195; //Method _Jack3_4:()V
   152:	return
   153:	aload_0
   154:	getfield	#262; //Field efalse:Lspec/benchmarks/_228_jack/FalseException;
   157:	athrow

private void _Jack3_2();
   throws spec/benchmarks/_228_jack/TrueException, spec/benchmarks/_228_jack/FalseException
  Code:
   0:	aload_0
   1:	bipush	114
   3:	invokespecial	#313; //Method scan_token:(I)V
   6:	aload_0
   7:	bipush	77
   9:	invokespecial	#313; //Method scan_token:(I)V
   12:	aload_0
   13:	invokespecial	#226; //Method _Jack3integer_literal:()V
   16:	aload_0
   17:	bipush	74
   19:	invokespecial	#313; //Method scan_token:(I)V
   22:	return

private void _Jack3_3();
   throws spec/benchmarks/_228_jack/TrueException, spec/benchmarks/_228_jack/FalseException
  Code:
   0:	aload_0
   1:	bipush	115
   3:	invokespecial	#313; //Method scan_token:(I)V
   6:	aload_0
   7:	bipush	77
   9:	invokespecial	#313; //Method scan_token:(I)V
   12:	aload_0
   13:	invokespecial	#216; //Method _Jack3boolean_literal:()V
   16:	aload_0
   17:	bipush	74
   19:	invokespecial	#313; //Method scan_token:(I)V
   22:	return

private void _Jack3_4();
   throws spec/benchmarks/_228_jack/TrueException, spec/benchmarks/_228_jack/FalseException
  Code:
   0:	aload_0
   1:	bipush	116
   3:	invokespecial	#313; //Method scan_token:(I)V
   6:	aload_0
   7:	bipush	77
   9:	invokespecial	#313; //Method scan_token:(I)V
   12:	aload_0
   13:	invokespecial	#216; //Method _Jack3boolean_literal:()V
   16:	aload_0
   17:	bipush	74
   19:	invokespecial	#313; //Method scan_token:(I)V
   22:	return

private void _Jack3_5();
   throws spec/benchmarks/_228_jack/TrueException, spec/benchmarks/_228_jack/FalseException
  Code:
   0:	aload_0
   1:	invokespecial	#229; //Method _Jack3production:()V
   4:	return

private void _Jack3_6();
   throws spec/benchmarks/_228_jack/TrueException, spec/benchmarks/_228_jack/FalseException
  Code:
   0:	aload_0
   1:	bipush	63
   3:	invokespecial	#313; //Method scan_token:(I)V
   6:	return

private void _Jack3_7();
   throws spec/benchmarks/_228_jack/TrueException, spec/benchmarks/_228_jack/FalseException
  Code:
   0:	aload_0
   1:	bipush	64
   3:	invokespecial	#313; //Method scan_token:(I)V
   6:	return

private void _Jack3_8();
   throws spec/benchmarks/_228_jack/TrueException, spec/benchmarks/_228_jack/FalseException
  Code:
   0:	aload_0
   1:	bipush	119
   3:	invokespecial	#313; //Method scan_token:(I)V
   6:	aload_0
   7:	invokespecial	#227; //Method _Jack3java_return_type:()V
   10:	aload_0
   11:	invokespecial	#225; //Method _Jack3identifier:()V
   14:	aload_0
   15:	bipush	68
   17:	invokespecial	#313; //Method scan_token:(I)V
   20:	aload_0
   21:	invokespecial	#268; //Method etrue_thrower:()V
   24:	aload_0
   25:	bipush	69
   27:	invokespecial	#313; //Method scan_token:(I)V
   30:	aload_0
   31:	bipush	70
   33:	invokespecial	#313; //Method scan_token:(I)V
   36:	aload_0
   37:	invokespecial	#268; //Method etrue_thrower:()V
   40:	aload_0
   41:	bipush	71
   43:	invokespecial	#313; //Method scan_token:(I)V
   46:	return

private void _Jack3_9();
   throws spec/benchmarks/_228_jack/TrueException, spec/benchmarks/_228_jack/FalseException
  Code:
   0:	aload_0
   1:	invokespecial	#228; //Method _Jack3method_declaration:()V
   4:	aload_0
   5:	bipush	83
   7:	invokespecial	#313; //Method scan_token:(I)V
   10:	aload_0
   11:	bipush	70
   13:	invokespecial	#313; //Method scan_token:(I)V
   16:	aload_0
   17:	invokespecial	#268; //Method etrue_thrower:()V
   20:	aload_0
   21:	bipush	71
   23:	invokespecial	#313; //Method scan_token:(I)V
   26:	aload_0
   27:	bipush	70
   29:	invokespecial	#313; //Method scan_token:(I)V
   32:	aload_0
   33:	invokespecial	#223; //Method _Jack3expansion_choices:()V
   36:	aload_0
   37:	bipush	71
   39:	invokespecial	#313; //Method scan_token:(I)V
   42:	return

private void _Jack3_10();
   throws spec/benchmarks/_228_jack/TrueException, spec/benchmarks/_228_jack/FalseException
  Code:
   0:	aload_0
   1:	invokespecial	#227; //Method _Jack3java_return_type:()V
   4:	aload_0
   5:	invokespecial	#225; //Method _Jack3identifier:()V
   8:	aload_0
   9:	bipush	68
   11:	invokespecial	#313; //Method scan_token:(I)V
   14:	aload_0
   15:	invokespecial	#268; //Method etrue_thrower:()V
   18:	aload_0
   19:	bipush	69
   21:	invokespecial	#313; //Method scan_token:(I)V
   24:	return

private void _Jack3_11();
   throws spec/benchmarks/_228_jack/TrueException, spec/benchmarks/_228_jack/FalseException
  Code:
   0:	aload_0
   1:	bipush	120
   3:	invokespecial	#313; //Method scan_token:(I)V
   6:	return

private void _Jack3_12();
   throws spec/benchmarks/_228_jack/TrueException, spec/benchmarks/_228_jack/FalseException
  Code:
   0:	aload_0
   1:	bipush	121
   3:	invokespecial	#313; //Method scan_token:(I)V
   6:	return

private void _Jack3_13();
   throws spec/benchmarks/_228_jack/TrueException, spec/benchmarks/_228_jack/FalseException
  Code:
   0:	aload_0
   1:	bipush	97
   3:	invokespecial	#313; //Method scan_token:(I)V
   6:	aload_0
   7:	invokespecial	#222; //Method _Jack3expansion:()V
   10:	return

private void _Jack3_14();
   throws spec/benchmarks/_228_jack/TrueException, spec/benchmarks/_228_jack/FalseException
  Code:
   0:	aload_0
   1:	invokespecial	#224; //Method _Jack3expansion_unit:()V
   4:	return

private void _Jack3_15();
   throws spec/benchmarks/_228_jack/TrueException, spec/benchmarks/_228_jack/FalseException
  Code:
   0:	aload_0
   1:	invokespecial	#230; //Method _Jack3regular_expression:()V
   4:	return

private void _Jack3_16();
   throws spec/benchmarks/_228_jack/TrueException, spec/benchmarks/_228_jack/FalseException
  Code:
   0:	aload_0
   1:	getfield	#289; //Field la:I
   4:	istore_1
   5:	aload_0
   6:	getfield	#281; //Field index:I
   9:	istore_2
   10:	aload_0
   11:	aload_0
   12:	iload_1
   13:	iconst_3
   14:	if_icmple	21
   17:	iconst_3
   18:	goto	22
   21:	iload_1
   22:	iload_2
   23:	invokespecial	#116; //Method _Jack2_17:(II)Z
   26:	putfield	#252; //Field cond:Z
   29:	aload_0
   30:	iload_1
   31:	putfield	#289; //Field la:I
   34:	aload_0
   35:	iload_2
   36:	putfield	#281; //Field index:I
   39:	aload_0
   40:	getfield	#252; //Field cond:Z
   43:	ifeq	50
   46:	aload_0
   47:	invokespecial	#170; //Method _Jack3_17:()V
   50:	aload_0
   51:	invokespecial	#225; //Method _Jack3identifier:()V
   54:	aload_0
   55:	bipush	68
   57:	invokespecial	#313; //Method scan_token:(I)V
   60:	aload_0
   61:	invokespecial	#268; //Method etrue_thrower:()V
   64:	aload_0
   65:	bipush	69
   67:	invokespecial	#313; //Method scan_token:(I)V
   70:	return

private void _Jack3_17();
   throws spec/benchmarks/_228_jack/TrueException, spec/benchmarks/_228_jack/FalseException
  Code:
   0:	aload_0
   1:	invokespecial	#225; //Method _Jack3identifier:()V
   4:	aload_0
   5:	bipush	77
   7:	invokespecial	#313; //Method scan_token:(I)V
   10:	return

private void _Jack3_18();
   throws spec/benchmarks/_228_jack/TrueException, spec/benchmarks/_228_jack/FalseException
  Code:
   0:	aload_0
   1:	bipush	70
   3:	invokespecial	#313; //Method scan_token:(I)V
   6:	aload_0
   7:	invokespecial	#268; //Method etrue_thrower:()V
   10:	aload_0
   11:	bipush	71
   13:	invokespecial	#313; //Method scan_token:(I)V
   16:	return

private void _Jack3_19();
   throws spec/benchmarks/_228_jack/TrueException, spec/benchmarks/_228_jack/FalseException
  Code:
   0:	aload_0
   1:	bipush	68
   3:	invokespecial	#313; //Method scan_token:(I)V
   6:	aload_0
   7:	invokespecial	#223; //Method _Jack3expansion_choices:()V
   10:	aload_0
   11:	bipush	69
   13:	invokespecial	#313; //Method scan_token:(I)V
   16:	aload_0
   17:	getfield	#289; //Field la:I
   20:	istore_1
   21:	aload_0
   22:	getfield	#281; //Field index:I
   25:	istore_2
   26:	aload_0
   27:	aload_0
   28:	iload_1
   29:	iconst_3
   30:	if_icmple	37
   33:	iconst_3
   34:	goto	38
   37:	iload_1
   38:	iload_2
   39:	invokespecial	#120; //Method _Jack2_20:(II)Z
   42:	putfield	#252; //Field cond:Z
   45:	aload_0
   46:	iload_1
   47:	putfield	#289; //Field la:I
   50:	aload_0
   51:	iload_2
   52:	putfield	#281; //Field index:I
   55:	aload_0
   56:	getfield	#252; //Field cond:Z
   59:	ifeq	66
   62:	aload_0
   63:	invokespecial	#174; //Method _Jack3_20:()V
   66:	return

private void _Jack3_20();
   throws spec/benchmarks/_228_jack/TrueException, spec/benchmarks/_228_jack/FalseException
  Code:
   0:	aload_0
   1:	getfield	#289; //Field la:I
   4:	istore_1
   5:	aload_0
   6:	getfield	#281; //Field index:I
   9:	istore_2
   10:	aload_0
   11:	aload_0
   12:	iload_1
   13:	iconst_3
   14:	if_icmple	21
   17:	iconst_3
   18:	goto	22
   21:	iload_1
   22:	iload_2
   23:	invokespecial	#121; //Method _Jack2_21:(II)Z
   26:	putfield	#252; //Field cond:Z
   29:	aload_0
   30:	iload_1
   31:	putfield	#289; //Field la:I
   34:	aload_0
   35:	iload_2
   36:	putfield	#281; //Field index:I
   39:	aload_0
   40:	getfield	#252; //Field cond:Z
   43:	ifeq	51
   46:	aload_0
   47:	invokespecial	#175; //Method _Jack3_21:()V
   50:	return
   51:	aload_0
   52:	getfield	#289; //Field la:I
   55:	istore_1
   56:	aload_0
   57:	getfield	#281; //Field index:I
   60:	istore_2
   61:	aload_0
   62:	aload_0
   63:	iload_1
   64:	iconst_3
   65:	if_icmple	72
   68:	iconst_3
   69:	goto	73
   72:	iload_1
   73:	iload_2
   74:	invokespecial	#122; //Method _Jack2_22:(II)Z
   77:	putfield	#252; //Field cond:Z
   80:	aload_0
   81:	iload_1
   82:	putfield	#289; //Field la:I
   85:	aload_0
   86:	iload_2
   87:	putfield	#281; //Field index:I
   90:	aload_0
   91:	getfield	#252; //Field cond:Z
   94:	ifeq	102
   97:	aload_0
   98:	invokespecial	#176; //Method _Jack3_22:()V
   101:	return
   102:	aload_0
   103:	getfield	#289; //Field la:I
   106:	istore_1
   107:	aload_0
   108:	getfield	#281; //Field index:I
   111:	istore_2
   112:	aload_0
   113:	aload_0
   114:	iload_1
   115:	iconst_3
   116:	if_icmple	123
   119:	iconst_3
   120:	goto	124
   123:	iload_1
   124:	iload_2
   125:	invokespecial	#123; //Method _Jack2_23:(II)Z
   128:	putfield	#252; //Field cond:Z
   131:	aload_0
   132:	iload_1
   133:	putfield	#289; //Field la:I
   136:	aload_0
   137:	iload_2
   138:	putfield	#281; //Field index:I
   141:	aload_0
   142:	getfield	#252; //Field cond:Z
   145:	ifeq	153
   148:	aload_0
   149:	invokespecial	#177; //Method _Jack3_23:()V
   152:	return
   153:	aload_0
   154:	getfield	#262; //Field efalse:Lspec/benchmarks/_228_jack/FalseException;
   157:	athrow

private void _Jack3_21();
   throws spec/benchmarks/_228_jack/TrueException, spec/benchmarks/_228_jack/FalseException
  Code:
   0:	aload_0
   1:	bipush	92
   3:	invokespecial	#313; //Method scan_token:(I)V
   6:	return

private void _Jack3_22();
   throws spec/benchmarks/_228_jack/TrueException, spec/benchmarks/_228_jack/FalseException
  Code:
   0:	aload_0
   1:	bipush	94
   3:	invokespecial	#313; //Method scan_token:(I)V
   6:	return

private void _Jack3_23();
   throws spec/benchmarks/_228_jack/TrueException, spec/benchmarks/_228_jack/FalseException
  Code:
   0:	aload_0
   1:	bipush	82
   3:	invokespecial	#313; //Method scan_token:(I)V
   6:	return

private void _Jack3_24();
   throws spec/benchmarks/_228_jack/TrueException, spec/benchmarks/_228_jack/FalseException
  Code:
   0:	aload_0
   1:	bipush	72
   3:	invokespecial	#313; //Method scan_token:(I)V
   6:	aload_0
   7:	invokespecial	#223; //Method _Jack3expansion_choices:()V
   10:	aload_0
   11:	bipush	73
   13:	invokespecial	#313; //Method scan_token:(I)V
   16:	return

private void _Jack3_25();
   throws spec/benchmarks/_228_jack/TrueException, spec/benchmarks/_228_jack/FalseException
  Code:
   0:	aload_0
   1:	bipush	60
   3:	invokespecial	#313; //Method scan_token:(I)V
   6:	return

private void _Jack3_26();
   throws spec/benchmarks/_228_jack/TrueException, spec/benchmarks/_228_jack/FalseException
  Code:
   0:	aload_0
   1:	bipush	10
   3:	invokespecial	#313; //Method scan_token:(I)V
   6:	return

private void _Jack3_27();
   throws spec/benchmarks/_228_jack/TrueException, spec/benchmarks/_228_jack/FalseException
  Code:
   0:	aload_0
   1:	bipush	49
   3:	invokespecial	#313; //Method scan_token:(I)V
   6:	return

private void _Jack3_28();
   throws spec/benchmarks/_228_jack/TrueException, spec/benchmarks/_228_jack/FalseException
  Code:
   0:	aload_0
   1:	bipush	35
   3:	invokespecial	#313; //Method scan_token:(I)V
   6:	return

private void _Jack3_29();
   throws spec/benchmarks/_228_jack/TrueException, spec/benchmarks/_228_jack/FalseException
  Code:
   0:	aload_0
   1:	bipush	37
   3:	invokespecial	#313; //Method scan_token:(I)V
   6:	return

private void _Jack3_30();
   throws spec/benchmarks/_228_jack/TrueException, spec/benchmarks/_228_jack/FalseException
  Code:
   0:	aload_0
   1:	bipush	25
   3:	invokespecial	#313; //Method scan_token:(I)V
   6:	return

private void _Jack3_31();
   throws spec/benchmarks/_228_jack/TrueException, spec/benchmarks/_228_jack/FalseException
  Code:
   0:	aload_0
   1:	bipush	20
   3:	invokespecial	#313; //Method scan_token:(I)V
   6:	return

private void _Jack3_32();
   throws spec/benchmarks/_228_jack/TrueException, spec/benchmarks/_228_jack/FalseException
  Code:
   0:	aload_0
   1:	bipush	14
   3:	invokespecial	#313; //Method scan_token:(I)V
   6:	return

private void _Jack3_33();
   throws spec/benchmarks/_228_jack/TrueException, spec/benchmarks/_228_jack/FalseException
  Code:
   0:	aload_0
   1:	bipush	8
   3:	invokespecial	#313; //Method scan_token:(I)V
   6:	return

private void _Jack3_34();
   throws spec/benchmarks/_228_jack/TrueException, spec/benchmarks/_228_jack/FalseException
  Code:
   0:	aload_0
   1:	invokespecial	#225; //Method _Jack3identifier:()V
   4:	return

private void _Jack3_35();
   throws spec/benchmarks/_228_jack/TrueException, spec/benchmarks/_228_jack/FalseException
  Code:
   0:	aload_0
   1:	bipush	72
   3:	invokespecial	#313; //Method scan_token:(I)V
   6:	aload_0
   7:	bipush	73
   9:	invokespecial	#313; //Method scan_token:(I)V
   12:	return

private void _Jack3_36();
   throws spec/benchmarks/_228_jack/TrueException, spec/benchmarks/_228_jack/FalseException
  Code:
   0:	aload_0
   1:	invokespecial	#231; //Method _Jack3string_literal:()V
   4:	return

private void _Jack3_37();
   throws spec/benchmarks/_228_jack/TrueException, spec/benchmarks/_228_jack/FalseException
  Code:
   0:	aload_0
   1:	bipush	79
   3:	invokespecial	#313; //Method scan_token:(I)V
   6:	aload_0
   7:	getfield	#289; //Field la:I
   10:	istore_1
   11:	aload_0
   12:	getfield	#281; //Field index:I
   15:	istore_2
   16:	aload_0
   17:	aload_0
   18:	iload_1
   19:	iconst_3
   20:	if_icmple	27
   23:	iconst_3
   24:	goto	28
   27:	iload_1
   28:	iload_2
   29:	invokespecial	#139; //Method _Jack2_38:(II)Z
   32:	putfield	#252; //Field cond:Z
   35:	aload_0
   36:	iload_1
   37:	putfield	#289; //Field la:I
   40:	aload_0
   41:	iload_2
   42:	putfield	#281; //Field index:I
   45:	aload_0
   46:	getfield	#252; //Field cond:Z
   49:	ifeq	56
   52:	aload_0
   53:	invokespecial	#193; //Method _Jack3_38:()V
   56:	aload_0
   57:	invokespecial	#220; //Method _Jack3complex_regular_expression_choices:()V
   60:	aload_0
   61:	bipush	78
   63:	invokespecial	#313; //Method scan_token:(I)V
   66:	return

private void _Jack3_38();
   throws spec/benchmarks/_228_jack/TrueException, spec/benchmarks/_228_jack/FalseException
  Code:
   0:	aload_0
   1:	invokespecial	#225; //Method _Jack3identifier:()V
   4:	aload_0
   5:	bipush	83
   7:	invokespecial	#313; //Method scan_token:(I)V
   10:	return

private void _Jack3_39();
   throws spec/benchmarks/_228_jack/TrueException, spec/benchmarks/_228_jack/FalseException
  Code:
   0:	aload_0
   1:	bipush	79
   3:	invokespecial	#313; //Method scan_token:(I)V
   6:	aload_0
   7:	invokespecial	#225; //Method _Jack3identifier:()V
   10:	aload_0
   11:	bipush	78
   13:	invokespecial	#313; //Method scan_token:(I)V
   16:	return

private void _Jack3_40();
   throws spec/benchmarks/_228_jack/TrueException, spec/benchmarks/_228_jack/FalseException
  Code:
   0:	aload_0
   1:	bipush	79
   3:	invokespecial	#313; //Method scan_token:(I)V
   6:	aload_0
   7:	bipush	122
   9:	invokespecial	#313; //Method scan_token:(I)V
   12:	aload_0
   13:	bipush	78
   15:	invokespecial	#313; //Method scan_token:(I)V
   18:	return

private void _Jack3_41();
   throws spec/benchmarks/_228_jack/TrueException, spec/benchmarks/_228_jack/FalseException
  Code:
   0:	aload_0
   1:	bipush	97
   3:	invokespecial	#313; //Method scan_token:(I)V
   6:	aload_0
   7:	invokespecial	#219; //Method _Jack3complex_regular_expression:()V
   10:	return

private void _Jack3_42();
   throws spec/benchmarks/_228_jack/TrueException, spec/benchmarks/_228_jack/FalseException
  Code:
   0:	aload_0
   1:	invokespecial	#221; //Method _Jack3complex_regular_expression_unit:()V
   4:	return

private void _Jack3_43();
   throws spec/benchmarks/_228_jack/TrueException, spec/benchmarks/_228_jack/FalseException
  Code:
   0:	aload_0
   1:	invokespecial	#231; //Method _Jack3string_literal:()V
   4:	return

private void _Jack3_44();
   throws spec/benchmarks/_228_jack/TrueException, spec/benchmarks/_228_jack/FalseException
  Code:
   0:	aload_0
   1:	bipush	79
   3:	invokespecial	#313; //Method scan_token:(I)V
   6:	aload_0
   7:	invokespecial	#225; //Method _Jack3identifier:()V
   10:	aload_0
   11:	bipush	78
   13:	invokespecial	#313; //Method scan_token:(I)V
   16:	return

private void _Jack3_45();
   throws spec/benchmarks/_228_jack/TrueException, spec/benchmarks/_228_jack/FalseException
  Code:
   0:	aload_0
   1:	invokespecial	#218; //Method _Jack3character_list:()V
   4:	return

private void _Jack3_46();
   throws spec/benchmarks/_228_jack/TrueException, spec/benchmarks/_228_jack/FalseException
  Code:
   0:	aload_0
   1:	bipush	68
   3:	invokespecial	#313; //Method scan_token:(I)V
   6:	aload_0
   7:	invokespecial	#220; //Method _Jack3complex_regular_expression_choices:()V
   10:	aload_0
   11:	bipush	69
   13:	invokespecial	#313; //Method scan_token:(I)V
   16:	aload_0
   17:	getfield	#289; //Field la:I
   20:	istore_1
   21:	aload_0
   22:	getfield	#281; //Field index:I
   25:	istore_2
   26:	aload_0
   27:	aload_0
   28:	iload_1
   29:	iconst_3
   30:	if_icmple	37
   33:	iconst_3
   34:	goto	38
   37:	iload_1
   38:	iload_2
   39:	invokespecial	#149; //Method _Jack2_47:(II)Z
   42:	putfield	#252; //Field cond:Z
   45:	aload_0
   46:	iload_1
   47:	putfield	#289; //Field la:I
   50:	aload_0
   51:	iload_2
   52:	putfield	#281; //Field index:I
   55:	aload_0
   56:	getfield	#252; //Field cond:Z
   59:	ifeq	66
   62:	aload_0
   63:	invokespecial	#203; //Method _Jack3_47:()V
   66:	return

private void _Jack3_47();
   throws spec/benchmarks/_228_jack/TrueException, spec/benchmarks/_228_jack/FalseException
  Code:
   0:	aload_0
   1:	getfield	#289; //Field la:I
   4:	istore_1
   5:	aload_0
   6:	getfield	#281; //Field index:I
   9:	istore_2
   10:	aload_0
   11:	aload_0
   12:	iload_1
   13:	iconst_3
   14:	if_icmple	21
   17:	iconst_3
   18:	goto	22
   21:	iload_1
   22:	iload_2
   23:	invokespecial	#150; //Method _Jack2_48:(II)Z
   26:	putfield	#252; //Field cond:Z
   29:	aload_0
   30:	iload_1
   31:	putfield	#289; //Field la:I
   34:	aload_0
   35:	iload_2
   36:	putfield	#281; //Field index:I
   39:	aload_0
   40:	getfield	#252; //Field cond:Z
   43:	ifeq	51
   46:	aload_0
   47:	invokespecial	#204; //Method _Jack3_48:()V
   50:	return
   51:	aload_0
   52:	getfield	#289; //Field la:I
   55:	istore_1
   56:	aload_0
   57:	getfield	#281; //Field index:I
   60:	istore_2
   61:	aload_0
   62:	aload_0
   63:	iload_1
   64:	iconst_3
   65:	if_icmple	72
   68:	iconst_3
   69:	goto	73
   72:	iload_1
   73:	iload_2
   74:	invokespecial	#151; //Method _Jack2_49:(II)Z
   77:	putfield	#252; //Field cond:Z
   80:	aload_0
   81:	iload_1
   82:	putfield	#289; //Field la:I
   85:	aload_0
   86:	iload_2
   87:	putfield	#281; //Field index:I
   90:	aload_0
   91:	getfield	#252; //Field cond:Z
   94:	ifeq	102
   97:	aload_0
   98:	invokespecial	#205; //Method _Jack3_49:()V
   101:	return
   102:	aload_0
   103:	getfield	#289; //Field la:I
   106:	istore_1
   107:	aload_0
   108:	getfield	#281; //Field index:I
   111:	istore_2
   112:	aload_0
   113:	aload_0
   114:	iload_1
   115:	iconst_3
   116:	if_icmple	123
   119:	iconst_3
   120:	goto	124
   123:	iload_1
   124:	iload_2
   125:	invokespecial	#153; //Method _Jack2_50:(II)Z
   128:	putfield	#252; //Field cond:Z
   131:	aload_0
   132:	iload_1
   133:	putfield	#289; //Field la:I
   136:	aload_0
   137:	iload_2
   138:	putfield	#281; //Field index:I
   141:	aload_0
   142:	getfield	#252; //Field cond:Z
   145:	ifeq	153
   148:	aload_0
   149:	invokespecial	#207; //Method _Jack3_50:()V
   152:	return
   153:	aload_0
   154:	getfield	#262; //Field efalse:Lspec/benchmarks/_228_jack/FalseException;
   157:	athrow

private void _Jack3_48();
   throws spec/benchmarks/_228_jack/TrueException, spec/benchmarks/_228_jack/FalseException
  Code:
   0:	aload_0
   1:	bipush	92
   3:	invokespecial	#313; //Method scan_token:(I)V
   6:	return

private void _Jack3_49();
   throws spec/benchmarks/_228_jack/TrueException, spec/benchmarks/_228_jack/FalseException
  Code:
   0:	aload_0
   1:	bipush	94
   3:	invokespecial	#313; //Method scan_token:(I)V
   6:	return

private void _Jack3_50();
   throws spec/benchmarks/_228_jack/TrueException, spec/benchmarks/_228_jack/FalseException
  Code:
   0:	aload_0
   1:	bipush	82
   3:	invokespecial	#313; //Method scan_token:(I)V
   6:	return

private void _Jack3_51();
   throws spec/benchmarks/_228_jack/TrueException, spec/benchmarks/_228_jack/FalseException
  Code:
   0:	aload_0
   1:	bipush	81
   3:	invokespecial	#313; //Method scan_token:(I)V
   6:	return

private void _Jack3_52();
   throws spec/benchmarks/_228_jack/TrueException, spec/benchmarks/_228_jack/FalseException
  Code:
   0:	aload_0
   1:	invokespecial	#217; //Method _Jack3character_descriptor:()V
   4:	aload_0
   5:	getfield	#289; //Field la:I
   8:	istore_1
   9:	aload_0
   10:	getfield	#281; //Field index:I
   13:	istore_2
   14:	aload_0
   15:	aload_0
   16:	iload_1
   17:	iconst_3
   18:	if_icmple	25
   21:	iconst_3
   22:	goto	26
   25:	iload_1
   26:	iload_2
   27:	invokespecial	#156; //Method _Jack2_53:(II)Z
   30:	ifeq	37
   33:	iconst_0
   34:	goto	38
   37:	iconst_1
   38:	putfield	#252; //Field cond:Z
   41:	aload_0
   42:	iload_1
   43:	putfield	#289; //Field la:I
   46:	aload_0
   47:	iload_2
   48:	putfield	#281; //Field index:I
   51:	aload_0
   52:	getfield	#252; //Field cond:Z
   55:	ifne	65
   58:	aload_0
   59:	invokespecial	#210; //Method _Jack3_53:()V
   62:	goto	4
   65:	return

private void _Jack3_53();
   throws spec/benchmarks/_228_jack/TrueException, spec/benchmarks/_228_jack/FalseException
  Code:
   0:	aload_0
   1:	bipush	75
   3:	invokespecial	#313; //Method scan_token:(I)V
   6:	aload_0
   7:	invokespecial	#217; //Method _Jack3character_descriptor:()V
   10:	return

private void _Jack3_54();
   throws spec/benchmarks/_228_jack/TrueException, spec/benchmarks/_228_jack/FalseException
  Code:
   0:	aload_0
   1:	bipush	93
   3:	invokespecial	#313; //Method scan_token:(I)V
   6:	aload_0
   7:	invokespecial	#231; //Method _Jack3string_literal:()V
   10:	return

private void _Jack3integer_literal();
   throws spec/benchmarks/_228_jack/TrueException, spec/benchmarks/_228_jack/FalseException
  Code:
   0:	aload_0
   1:	bipush	65
   3:	invokespecial	#313; //Method scan_token:(I)V
   6:	return

private void _Jack3boolean_literal();
   throws spec/benchmarks/_228_jack/TrueException, spec/benchmarks/_228_jack/FalseException
  Code:
   0:	aload_0
   1:	getfield	#289; //Field la:I
   4:	istore_1
   5:	aload_0
   6:	getfield	#281; //Field index:I
   9:	istore_2
   10:	aload_0
   11:	aload_0
   12:	iload_1
   13:	iconst_3
   14:	if_icmple	21
   17:	iconst_3
   18:	goto	22
   21:	iload_1
   22:	iload_2
   23:	invokespecial	#158; //Method _Jack2_6:(II)Z
   26:	putfield	#252; //Field cond:Z
   29:	aload_0
   30:	iload_1
   31:	putfield	#289; //Field la:I
   34:	aload_0
   35:	iload_2
   36:	putfield	#281; //Field index:I
   39:	aload_0
   40:	getfield	#252; //Field cond:Z
   43:	ifeq	51
   46:	aload_0
   47:	invokespecial	#212; //Method _Jack3_6:()V
   50:	return
   51:	aload_0
   52:	getfield	#289; //Field la:I
   55:	istore_1
   56:	aload_0
   57:	getfield	#281; //Field index:I
   60:	istore_2
   61:	aload_0
   62:	aload_0
   63:	iload_1
   64:	iconst_3
   65:	if_icmple	72
   68:	iconst_3
   69:	goto	73
   72:	iload_1
   73:	iload_2
   74:	invokespecial	#159; //Method _Jack2_7:(II)Z
   77:	putfield	#252; //Field cond:Z
   80:	aload_0
   81:	iload_1
   82:	putfield	#289; //Field la:I
   85:	aload_0
   86:	iload_2
   87:	putfield	#281; //Field index:I
   90:	aload_0
   91:	getfield	#252; //Field cond:Z
   94:	ifeq	102
   97:	aload_0
   98:	invokespecial	#213; //Method _Jack3_7:()V
   101:	return
   102:	aload_0
   103:	getfield	#262; //Field efalse:Lspec/benchmarks/_228_jack/FalseException;
   106:	athrow

private void _Jack3production();
   throws spec/benchmarks/_228_jack/TrueException, spec/benchmarks/_228_jack/FalseException
  Code:
   0:	aload_0
   1:	getfield	#289; //Field la:I
   4:	istore_1
   5:	aload_0
   6:	getfield	#281; //Field index:I
   9:	istore_2
   10:	aload_0
   11:	aload_0
   12:	iload_1
   13:	iconst_3
   14:	if_icmple	21
   17:	iconst_3
   18:	goto	22
   21:	iload_1
   22:	iload_2
   23:	invokespecial	#160; //Method _Jack2_8:(II)Z
   26:	putfield	#252; //Field cond:Z
   29:	aload_0
   30:	iload_1
   31:	putfield	#289; //Field la:I
   34:	aload_0
   35:	iload_2
   36:	putfield	#281; //Field index:I
   39:	aload_0
   40:	getfield	#252; //Field cond:Z
   43:	ifeq	51
   46:	aload_0
   47:	invokespecial	#214; //Method _Jack3_8:()V
   50:	return
   51:	aload_0
   52:	getfield	#289; //Field la:I
   55:	istore_1
   56:	aload_0
   57:	getfield	#281; //Field index:I
   60:	istore_2
   61:	aload_0
   62:	aload_0
   63:	iload_1
   64:	iconst_3
   65:	if_icmple	72
   68:	iconst_3
   69:	goto	73
   72:	iload_1
   73:	iload_2
   74:	invokespecial	#161; //Method _Jack2_9:(II)Z
   77:	putfield	#252; //Field cond:Z
   80:	aload_0
   81:	iload_1
   82:	putfield	#289; //Field la:I
   85:	aload_0
   86:	iload_2
   87:	putfield	#281; //Field index:I
   90:	aload_0
   91:	getfield	#252; //Field cond:Z
   94:	ifeq	102
   97:	aload_0
   98:	invokespecial	#215; //Method _Jack3_9:()V
   101:	return
   102:	aload_0
   103:	getfield	#262; //Field efalse:Lspec/benchmarks/_228_jack/FalseException;
   106:	athrow

private void _Jack3java_return_type();
   throws spec/benchmarks/_228_jack/TrueException, spec/benchmarks/_228_jack/FalseException
  Code:
   0:	aload_0
   1:	getfield	#289; //Field la:I
   4:	istore_1
   5:	aload_0
   6:	getfield	#281; //Field index:I
   9:	istore_2
   10:	aload_0
   11:	aload_0
   12:	iload_1
   13:	iconst_3
   14:	if_icmple	21
   17:	iconst_3
   18:	goto	22
   21:	iload_1
   22:	iload_2
   23:	invokespecial	#125; //Method _Jack2_25:(II)Z
   26:	putfield	#252; //Field cond:Z
   29:	aload_0
   30:	iload_1
   31:	putfield	#289; //Field la:I
   34:	aload_0
   35:	iload_2
   36:	putfield	#281; //Field index:I
   39:	aload_0
   40:	getfield	#252; //Field cond:Z
   43:	ifeq	53
   46:	aload_0
   47:	invokespecial	#179; //Method _Jack3_25:()V
   50:	goto	535
   53:	aload_0
   54:	getfield	#289; //Field la:I
   57:	istore_1
   58:	aload_0
   59:	getfield	#281; //Field index:I
   62:	istore_2
   63:	aload_0
   64:	aload_0
   65:	iload_1
   66:	iconst_3
   67:	if_icmple	74
   70:	iconst_3
   71:	goto	75
   74:	iload_1
   75:	iload_2
   76:	invokespecial	#126; //Method _Jack2_26:(II)Z
   79:	putfield	#252; //Field cond:Z
   82:	aload_0
   83:	iload_1
   84:	putfield	#289; //Field la:I
   87:	aload_0
   88:	iload_2
   89:	putfield	#281; //Field index:I
   92:	aload_0
   93:	getfield	#252; //Field cond:Z
   96:	ifeq	106
   99:	aload_0
   100:	invokespecial	#180; //Method _Jack3_26:()V
   103:	goto	535
   106:	aload_0
   107:	getfield	#289; //Field la:I
   110:	istore_1
   111:	aload_0
   112:	getfield	#281; //Field index:I
   115:	istore_2
   116:	aload_0
   117:	aload_0
   118:	iload_1
   119:	iconst_3
   120:	if_icmple	127
   123:	iconst_3
   124:	goto	128
   127:	iload_1
   128:	iload_2
   129:	invokespecial	#127; //Method _Jack2_27:(II)Z
   132:	putfield	#252; //Field cond:Z
   135:	aload_0
   136:	iload_1
   137:	putfield	#289; //Field la:I
   140:	aload_0
   141:	iload_2
   142:	putfield	#281; //Field index:I
   145:	aload_0
   146:	getfield	#252; //Field cond:Z
   149:	ifeq	159
   152:	aload_0
   153:	invokespecial	#181; //Method _Jack3_27:()V
   156:	goto	535
   159:	aload_0
   160:	getfield	#289; //Field la:I
   163:	istore_1
   164:	aload_0
   165:	getfield	#281; //Field index:I
   168:	istore_2
   169:	aload_0
   170:	aload_0
   171:	iload_1
   172:	iconst_3
   173:	if_icmple	180
   176:	iconst_3
   177:	goto	181
   180:	iload_1
   181:	iload_2
   182:	invokespecial	#128; //Method _Jack2_28:(II)Z
   185:	putfield	#252; //Field cond:Z
   188:	aload_0
   189:	iload_1
   190:	putfield	#289; //Field la:I
   193:	aload_0
   194:	iload_2
   195:	putfield	#281; //Field index:I
   198:	aload_0
   199:	getfield	#252; //Field cond:Z
   202:	ifeq	212
   205:	aload_0
   206:	invokespecial	#182; //Method _Jack3_28:()V
   209:	goto	535
   212:	aload_0
   213:	getfield	#289; //Field la:I
   216:	istore_1
   217:	aload_0
   218:	getfield	#281; //Field index:I
   221:	istore_2
   222:	aload_0
   223:	aload_0
   224:	iload_1
   225:	iconst_3
   226:	if_icmple	233
   229:	iconst_3
   230:	goto	234
   233:	iload_1
   234:	iload_2
   235:	invokespecial	#129; //Method _Jack2_29:(II)Z
   238:	putfield	#252; //Field cond:Z
   241:	aload_0
   242:	iload_1
   243:	putfield	#289; //Field la:I
   246:	aload_0
   247:	iload_2
   248:	putfield	#281; //Field index:I
   251:	aload_0
   252:	getfield	#252; //Field cond:Z
   255:	ifeq	265
   258:	aload_0
   259:	invokespecial	#183; //Method _Jack3_29:()V
   262:	goto	535
   265:	aload_0
   266:	getfield	#289; //Field la:I
   269:	istore_1
   270:	aload_0
   271:	getfield	#281; //Field index:I
   274:	istore_2
   275:	aload_0
   276:	aload_0
   277:	iload_1
   278:	iconst_3
   279:	if_icmple	286
   282:	iconst_3
   283:	goto	287
   286:	iload_1
   287:	iload_2
   288:	invokespecial	#131; //Method _Jack2_30:(II)Z
   291:	putfield	#252; //Field cond:Z
   294:	aload_0
   295:	iload_1
   296:	putfield	#289; //Field la:I
   299:	aload_0
   300:	iload_2
   301:	putfield	#281; //Field index:I
   304:	aload_0
   305:	getfield	#252; //Field cond:Z
   308:	ifeq	318
   311:	aload_0
   312:	invokespecial	#185; //Method _Jack3_30:()V
   315:	goto	535
   318:	aload_0
   319:	getfield	#289; //Field la:I
   322:	istore_1
   323:	aload_0
   324:	getfield	#281; //Field index:I
   327:	istore_2
   328:	aload_0
   329:	aload_0
   330:	iload_1
   331:	iconst_3
   332:	if_icmple	339
   335:	iconst_3
   336:	goto	340
   339:	iload_1
   340:	iload_2
   341:	invokespecial	#132; //Method _Jack2_31:(II)Z
   344:	putfield	#252; //Field cond:Z
   347:	aload_0
   348:	iload_1
   349:	putfield	#289; //Field la:I
   352:	aload_0
   353:	iload_2
   354:	putfield	#281; //Field index:I
   357:	aload_0
   358:	getfield	#252; //Field cond:Z
   361:	ifeq	371
   364:	aload_0
   365:	invokespecial	#186; //Method _Jack3_31:()V
   368:	goto	535
   371:	aload_0
   372:	getfield	#289; //Field la:I
   375:	istore_1
   376:	aload_0
   377:	getfield	#281; //Field index:I
   380:	istore_2
   381:	aload_0
   382:	aload_0
   383:	iload_1
   384:	iconst_3
   385:	if_icmple	392
   388:	iconst_3
   389:	goto	393
   392:	iload_1
   393:	iload_2
   394:	invokespecial	#133; //Method _Jack2_32:(II)Z
   397:	putfield	#252; //Field cond:Z
   400:	aload_0
   401:	iload_1
   402:	putfield	#289; //Field la:I
   405:	aload_0
   406:	iload_2
   407:	putfield	#281; //Field index:I
   410:	aload_0
   411:	getfield	#252; //Field cond:Z
   414:	ifeq	424
   417:	aload_0
   418:	invokespecial	#187; //Method _Jack3_32:()V
   421:	goto	535
   424:	aload_0
   425:	getfield	#289; //Field la:I
   428:	istore_1
   429:	aload_0
   430:	getfield	#281; //Field index:I
   433:	istore_2
   434:	aload_0
   435:	aload_0
   436:	iload_1
   437:	iconst_3
   438:	if_icmple	445
   441:	iconst_3
   442:	goto	446
   445:	iload_1
   446:	iload_2
   447:	invokespecial	#134; //Method _Jack2_33:(II)Z
   450:	putfield	#252; //Field cond:Z
   453:	aload_0
   454:	iload_1
   455:	putfield	#289; //Field la:I
   458:	aload_0
   459:	iload_2
   460:	putfield	#281; //Field index:I
   463:	aload_0
   464:	getfield	#252; //Field cond:Z
   467:	ifeq	477
   470:	aload_0
   471:	invokespecial	#188; //Method _Jack3_33:()V
   474:	goto	535
   477:	aload_0
   478:	getfield	#289; //Field la:I
   481:	istore_1
   482:	aload_0
   483:	getfield	#281; //Field index:I
   486:	istore_2
   487:	aload_0
   488:	aload_0
   489:	iload_1
   490:	iconst_3
   491:	if_icmple	498
   494:	iconst_3
   495:	goto	499
   498:	iload_1
   499:	iload_2
   500:	invokespecial	#135; //Method _Jack2_34:(II)Z
   503:	putfield	#252; //Field cond:Z
   506:	aload_0
   507:	iload_1
   508:	putfield	#289; //Field la:I
   511:	aload_0
   512:	iload_2
   513:	putfield	#281; //Field index:I
   516:	aload_0
   517:	getfield	#252; //Field cond:Z
   520:	ifeq	530
   523:	aload_0
   524:	invokespecial	#189; //Method _Jack3_34:()V
   527:	goto	535
   530:	aload_0
   531:	getfield	#262; //Field efalse:Lspec/benchmarks/_228_jack/FalseException;
   534:	athrow
   535:	aload_0
   536:	getfield	#289; //Field la:I
   539:	istore_1
   540:	aload_0
   541:	getfield	#281; //Field index:I
   544:	istore_2
   545:	aload_0
   546:	aload_0
   547:	iload_1
   548:	iconst_3
   549:	if_icmple	556
   552:	iconst_3
   553:	goto	557
   556:	iload_1
   557:	iload_2
   558:	invokespecial	#136; //Method _Jack2_35:(II)Z
   561:	ifeq	568
   564:	iconst_0
   565:	goto	569
   568:	iconst_1
   569:	putfield	#252; //Field cond:Z
   572:	aload_0
   573:	iload_1
   574:	putfield	#289; //Field la:I
   577:	aload_0
   578:	iload_2
   579:	putfield	#281; //Field index:I
   582:	aload_0
   583:	getfield	#252; //Field cond:Z
   586:	ifne	596
   589:	aload_0
   590:	invokespecial	#190; //Method _Jack3_35:()V
   593:	goto	535
   596:	return

private void _Jack3identifier();
   throws spec/benchmarks/_228_jack/TrueException, spec/benchmarks/_228_jack/FalseException
  Code:
   0:	aload_0
   1:	bipush	123
   3:	invokespecial	#313; //Method scan_token:(I)V
   6:	return

private void _Jack3method_declaration();
   throws spec/benchmarks/_228_jack/TrueException, spec/benchmarks/_228_jack/FalseException
  Code:
   0:	aload_0
   1:	getfield	#289; //Field la:I
   4:	istore_1
   5:	aload_0
   6:	getfield	#281; //Field index:I
   9:	istore_2
   10:	aload_0
   11:	aload_0
   12:	iload_1
   13:	iconst_3
   14:	if_icmple	21
   17:	iconst_3
   18:	goto	22
   21:	iload_1
   22:	iload_2
   23:	invokespecial	#109; //Method _Jack2_10:(II)Z
   26:	putfield	#252; //Field cond:Z
   29:	aload_0
   30:	iload_1
   31:	putfield	#289; //Field la:I
   34:	aload_0
   35:	iload_2
   36:	putfield	#281; //Field index:I
   39:	aload_0
   40:	getfield	#252; //Field cond:Z
   43:	ifeq	51
   46:	aload_0
   47:	invokespecial	#163; //Method _Jack3_10:()V
   50:	return
   51:	aload_0
   52:	getfield	#289; //Field la:I
   55:	istore_1
   56:	aload_0
   57:	getfield	#281; //Field index:I
   60:	istore_2
   61:	aload_0
   62:	aload_0
   63:	iload_1
   64:	iconst_3
   65:	if_icmple	72
   68:	iconst_3
   69:	goto	73
   72:	iload_1
   73:	iload_2
   74:	invokespecial	#110; //Method _Jack2_11:(II)Z
   77:	putfield	#252; //Field cond:Z
   80:	aload_0
   81:	iload_1
   82:	putfield	#289; //Field la:I
   85:	aload_0
   86:	iload_2
   87:	putfield	#281; //Field index:I
   90:	aload_0
   91:	getfield	#252; //Field cond:Z
   94:	ifeq	102
   97:	aload_0
   98:	invokespecial	#164; //Method _Jack3_11:()V
   101:	return
   102:	aload_0
   103:	getfield	#289; //Field la:I
   106:	istore_1
   107:	aload_0
   108:	getfield	#281; //Field index:I
   111:	istore_2
   112:	aload_0
   113:	aload_0
   114:	iload_1
   115:	iconst_3
   116:	if_icmple	123
   119:	iconst_3
   120:	goto	124
   123:	iload_1
   124:	iload_2
   125:	invokespecial	#111; //Method _Jack2_12:(II)Z
   128:	putfield	#252; //Field cond:Z
   131:	aload_0
   132:	iload_1
   133:	putfield	#289; //Field la:I
   136:	aload_0
   137:	iload_2
   138:	putfield	#281; //Field index:I
   141:	aload_0
   142:	getfield	#252; //Field cond:Z
   145:	ifeq	153
   148:	aload_0
   149:	invokespecial	#165; //Method _Jack3_12:()V
   152:	return
   153:	aload_0
   154:	getfield	#262; //Field efalse:Lspec/benchmarks/_228_jack/FalseException;
   157:	athrow

private void _Jack3expansion_choices();
   throws spec/benchmarks/_228_jack/TrueException, spec/benchmarks/_228_jack/FalseException
  Code:
   0:	aload_0
   1:	invokespecial	#222; //Method _Jack3expansion:()V
   4:	aload_0
   5:	getfield	#289; //Field la:I
   8:	istore_1
   9:	aload_0
   10:	getfield	#281; //Field index:I
   13:	istore_2
   14:	aload_0
   15:	aload_0
   16:	iload_1
   17:	iconst_3
   18:	if_icmple	25
   21:	iconst_3
   22:	goto	26
   25:	iload_1
   26:	iload_2
   27:	invokespecial	#112; //Method _Jack2_13:(II)Z
   30:	ifeq	37
   33:	iconst_0
   34:	goto	38
   37:	iconst_1
   38:	putfield	#252; //Field cond:Z
   41:	aload_0
   42:	iload_1
   43:	putfield	#289; //Field la:I
   46:	aload_0
   47:	iload_2
   48:	putfield	#281; //Field index:I
   51:	aload_0
   52:	getfield	#252; //Field cond:Z
   55:	ifne	65
   58:	aload_0
   59:	invokespecial	#166; //Method _Jack3_13:()V
   62:	goto	4
   65:	return

private void _Jack3expansion();
   throws spec/benchmarks/_228_jack/TrueException, spec/benchmarks/_228_jack/FalseException
  Code:
   0:	aload_0
   1:	invokespecial	#167; //Method _Jack3_14:()V
   4:	aload_0
   5:	getfield	#289; //Field la:I
   8:	istore_1
   9:	aload_0
   10:	getfield	#281; //Field index:I
   13:	istore_2
   14:	aload_0
   15:	aload_0
   16:	iload_1
   17:	iconst_3
   18:	if_icmple	25
   21:	iconst_3
   22:	goto	26
   25:	iload_1
   26:	iload_2
   27:	invokespecial	#113; //Method _Jack2_14:(II)Z
   30:	ifeq	37
   33:	iconst_0
   34:	goto	38
   37:	iconst_1
   38:	putfield	#252; //Field cond:Z
   41:	aload_0
   42:	iload_1
   43:	putfield	#289; //Field la:I
   46:	aload_0
   47:	iload_2
   48:	putfield	#281; //Field index:I
   51:	aload_0
   52:	getfield	#252; //Field cond:Z
   55:	ifeq	0
   58:	return

private void _Jack3expansion_unit();
   throws spec/benchmarks/_228_jack/TrueException, spec/benchmarks/_228_jack/FalseException
  Code:
   0:	aload_0
   1:	getfield	#289; //Field la:I
   4:	istore_1
   5:	aload_0
   6:	getfield	#281; //Field index:I
   9:	istore_2
   10:	aload_0
   11:	aload_0
   12:	iload_1
   13:	iconst_3
   14:	if_icmple	21
   17:	iconst_3
   18:	goto	22
   21:	iload_1
   22:	iload_2
   23:	invokespecial	#114; //Method _Jack2_15:(II)Z
   26:	putfield	#252; //Field cond:Z
   29:	aload_0
   30:	iload_1
   31:	putfield	#289; //Field la:I
   34:	aload_0
   35:	iload_2
   36:	putfield	#281; //Field index:I
   39:	aload_0
   40:	getfield	#252; //Field cond:Z
   43:	ifeq	51
   46:	aload_0
   47:	invokespecial	#168; //Method _Jack3_15:()V
   50:	return
   51:	aload_0
   52:	getfield	#289; //Field la:I
   55:	istore_1
   56:	aload_0
   57:	getfield	#281; //Field index:I
   60:	istore_2
   61:	aload_0
   62:	aload_0
   63:	iload_1
   64:	iconst_3
   65:	if_icmple	72
   68:	iconst_3
   69:	goto	73
   72:	iload_1
   73:	iload_2
   74:	invokespecial	#115; //Method _Jack2_16:(II)Z
   77:	putfield	#252; //Field cond:Z
   80:	aload_0
   81:	iload_1
   82:	putfield	#289; //Field la:I
   85:	aload_0
   86:	iload_2
   87:	putfield	#281; //Field index:I
   90:	aload_0
   91:	getfield	#252; //Field cond:Z
   94:	ifeq	102
   97:	aload_0
   98:	invokespecial	#169; //Method _Jack3_16:()V
   101:	return
   102:	aload_0
   103:	getfield	#289; //Field la:I
   106:	istore_1
   107:	aload_0
   108:	getfield	#281; //Field index:I
   111:	istore_2
   112:	aload_0
   113:	aload_0
   114:	iload_1
   115:	iconst_3
   116:	if_icmple	123
   119:	iconst_3
   120:	goto	124
   123:	iload_1
   124:	iload_2
   125:	invokespecial	#117; //Method _Jack2_18:(II)Z
   128:	putfield	#252; //Field cond:Z
   131:	aload_0
   132:	iload_1
   133:	putfield	#289; //Field la:I
   136:	aload_0
   137:	iload_2
   138:	putfield	#281; //Field index:I
   141:	aload_0
   142:	getfield	#252; //Field cond:Z
   145:	ifeq	153
   148:	aload_0
   149:	invokespecial	#171; //Method _Jack3_18:()V
   152:	return
   153:	aload_0
   154:	getfield	#289; //Field la:I
   157:	istore_1
   158:	aload_0
   159:	getfield	#281; //Field index:I
   162:	istore_2
   163:	aload_0
   164:	aload_0
   165:	iload_1
   166:	iconst_3
   167:	if_icmple	174
   170:	iconst_3
   171:	goto	175
   174:	iload_1
   175:	iload_2
   176:	invokespecial	#118; //Method _Jack2_19:(II)Z
   179:	putfield	#252; //Field cond:Z
   182:	aload_0
   183:	iload_1
   184:	putfield	#289; //Field la:I
   187:	aload_0
   188:	iload_2
   189:	putfield	#281; //Field index:I
   192:	aload_0
   193:	getfield	#252; //Field cond:Z
   196:	ifeq	204
   199:	aload_0
   200:	invokespecial	#172; //Method _Jack3_19:()V
   203:	return
   204:	aload_0
   205:	getfield	#289; //Field la:I
   208:	istore_1
   209:	aload_0
   210:	getfield	#281; //Field index:I
   213:	istore_2
   214:	aload_0
   215:	aload_0
   216:	iload_1
   217:	iconst_3
   218:	if_icmple	225
   221:	iconst_3
   222:	goto	226
   225:	iload_1
   226:	iload_2
   227:	invokespecial	#124; //Method _Jack2_24:(II)Z
   230:	putfield	#252; //Field cond:Z
   233:	aload_0
   234:	iload_1
   235:	putfield	#289; //Field la:I
   238:	aload_0
   239:	iload_2
   240:	putfield	#281; //Field index:I
   243:	aload_0
   244:	getfield	#252; //Field cond:Z
   247:	ifeq	255
   250:	aload_0
   251:	invokespecial	#178; //Method _Jack3_24:()V
   254:	return
   255:	aload_0
   256:	getfield	#262; //Field efalse:Lspec/benchmarks/_228_jack/FalseException;
   259:	athrow

private void _Jack3regular_expression();
   throws spec/benchmarks/_228_jack/TrueException, spec/benchmarks/_228_jack/FalseException
  Code:
   0:	aload_0
   1:	getfield	#289; //Field la:I
   4:	istore_1
   5:	aload_0
   6:	getfield	#281; //Field index:I
   9:	istore_2
   10:	aload_0
   11:	aload_0
   12:	iload_1
   13:	iconst_3
   14:	if_icmple	21
   17:	iconst_3
   18:	goto	22
   21:	iload_1
   22:	iload_2
   23:	invokespecial	#137; //Method _Jack2_36:(II)Z
   26:	putfield	#252; //Field cond:Z
   29:	aload_0
   30:	iload_1
   31:	putfield	#289; //Field la:I
   34:	aload_0
   35:	iload_2
   36:	putfield	#281; //Field index:I
   39:	aload_0
   40:	getfield	#252; //Field cond:Z
   43:	ifeq	51
   46:	aload_0
   47:	invokespecial	#191; //Method _Jack3_36:()V
   50:	return
   51:	aload_0
   52:	getfield	#289; //Field la:I
   55:	istore_1
   56:	aload_0
   57:	getfield	#281; //Field index:I
   60:	istore_2
   61:	aload_0
   62:	aload_0
   63:	iload_1
   64:	iconst_3
   65:	if_icmple	72
   68:	iconst_3
   69:	goto	73
   72:	iload_1
   73:	iload_2
   74:	invokespecial	#138; //Method _Jack2_37:(II)Z
   77:	putfield	#252; //Field cond:Z
   80:	aload_0
   81:	iload_1
   82:	putfield	#289; //Field la:I
   85:	aload_0
   86:	iload_2
   87:	putfield	#281; //Field index:I
   90:	aload_0
   91:	getfield	#252; //Field cond:Z
   94:	ifeq	102
   97:	aload_0
   98:	invokespecial	#192; //Method _Jack3_37:()V
   101:	return
   102:	aload_0
   103:	getfield	#289; //Field la:I
   106:	istore_1
   107:	aload_0
   108:	getfield	#281; //Field index:I
   111:	istore_2
   112:	aload_0
   113:	aload_0
   114:	iload_1
   115:	iconst_3
   116:	if_icmple	123
   119:	iconst_3
   120:	goto	124
   123:	iload_1
   124:	iload_2
   125:	invokespecial	#140; //Method _Jack2_39:(II)Z
   128:	putfield	#252; //Field cond:Z
   131:	aload_0
   132:	iload_1
   133:	putfield	#289; //Field la:I
   136:	aload_0
   137:	iload_2
   138:	putfield	#281; //Field index:I
   141:	aload_0
   142:	getfield	#252; //Field cond:Z
   145:	ifeq	153
   148:	aload_0
   149:	invokespecial	#194; //Method _Jack3_39:()V
   152:	return
   153:	aload_0
   154:	getfield	#289; //Field la:I
   157:	istore_1
   158:	aload_0
   159:	getfield	#281; //Field index:I
   162:	istore_2
   163:	aload_0
   164:	aload_0
   165:	iload_1
   166:	iconst_3
   167:	if_icmple	174
   170:	iconst_3
   171:	goto	175
   174:	iload_1
   175:	iload_2
   176:	invokespecial	#142; //Method _Jack2_40:(II)Z
   179:	putfield	#252; //Field cond:Z
   182:	aload_0
   183:	iload_1
   184:	putfield	#289; //Field la:I
   187:	aload_0
   188:	iload_2
   189:	putfield	#281; //Field index:I
   192:	aload_0
   193:	getfield	#252; //Field cond:Z
   196:	ifeq	204
   199:	aload_0
   200:	invokespecial	#196; //Method _Jack3_40:()V
   203:	return
   204:	aload_0
   205:	getfield	#262; //Field efalse:Lspec/benchmarks/_228_jack/FalseException;
   208:	athrow

private void _Jack3string_literal();
   throws spec/benchmarks/_228_jack/TrueException, spec/benchmarks/_228_jack/FalseException
  Code:
   0:	aload_0
   1:	bipush	66
   3:	invokespecial	#313; //Method scan_token:(I)V
   6:	return

private void _Jack3complex_regular_expression_choices();
   throws spec/benchmarks/_228_jack/TrueException, spec/benchmarks/_228_jack/FalseException
  Code:
   0:	aload_0
   1:	invokespecial	#219; //Method _Jack3complex_regular_expression:()V
   4:	aload_0
   5:	getfield	#289; //Field la:I
   8:	istore_1
   9:	aload_0
   10:	getfield	#281; //Field index:I
   13:	istore_2
   14:	aload_0
   15:	aload_0
   16:	iload_1
   17:	iconst_3
   18:	if_icmple	25
   21:	iconst_3
   22:	goto	26
   25:	iload_1
   26:	iload_2
   27:	invokespecial	#143; //Method _Jack2_41:(II)Z
   30:	ifeq	37
   33:	iconst_0
   34:	goto	38
   37:	iconst_1
   38:	putfield	#252; //Field cond:Z
   41:	aload_0
   42:	iload_1
   43:	putfield	#289; //Field la:I
   46:	aload_0
   47:	iload_2
   48:	putfield	#281; //Field index:I
   51:	aload_0
   52:	getfield	#252; //Field cond:Z
   55:	ifne	65
   58:	aload_0
   59:	invokespecial	#197; //Method _Jack3_41:()V
   62:	goto	4
   65:	return

private void _Jack3complex_regular_expression();
   throws spec/benchmarks/_228_jack/TrueException, spec/benchmarks/_228_jack/FalseException
  Code:
   0:	aload_0
   1:	invokespecial	#198; //Method _Jack3_42:()V
   4:	aload_0
   5:	getfield	#289; //Field la:I
   8:	istore_1
   9:	aload_0
   10:	getfield	#281; //Field index:I
   13:	istore_2
   14:	aload_0
   15:	aload_0
   16:	iload_1
   17:	iconst_3
   18:	if_icmple	25
   21:	iconst_3
   22:	goto	26
   25:	iload_1
   26:	iload_2
   27:	invokespecial	#144; //Method _Jack2_42:(II)Z
   30:	ifeq	37
   33:	iconst_0
   34:	goto	38
   37:	iconst_1
   38:	putfield	#252; //Field cond:Z
   41:	aload_0
   42:	iload_1
   43:	putfield	#289; //Field la:I
   46:	aload_0
   47:	iload_2
   48:	putfield	#281; //Field index:I
   51:	aload_0
   52:	getfield	#252; //Field cond:Z
   55:	ifeq	0
   58:	return

private void _Jack3complex_regular_expression_unit();
   throws spec/benchmarks/_228_jack/TrueException, spec/benchmarks/_228_jack/FalseException
  Code:
   0:	aload_0
   1:	getfield	#289; //Field la:I
   4:	istore_1
   5:	aload_0
   6:	getfield	#281; //Field index:I
   9:	istore_2
   10:	aload_0
   11:	aload_0
   12:	iload_1
   13:	iconst_3
   14:	if_icmple	21
   17:	iconst_3
   18:	goto	22
   21:	iload_1
   22:	iload_2
   23:	invokespecial	#145; //Method _Jack2_43:(II)Z
   26:	putfield	#252; //Field cond:Z
   29:	aload_0
   30:	iload_1
   31:	putfield	#289; //Field la:I
   34:	aload_0
   35:	iload_2
   36:	putfield	#281; //Field index:I
   39:	aload_0
   40:	getfield	#252; //Field cond:Z
   43:	ifeq	51
   46:	aload_0
   47:	invokespecial	#199; //Method _Jack3_43:()V
   50:	return
   51:	aload_0
   52:	getfield	#289; //Field la:I
   55:	istore_1
   56:	aload_0
   57:	getfield	#281; //Field index:I
   60:	istore_2
   61:	aload_0
   62:	aload_0
   63:	iload_1
   64:	iconst_3
   65:	if_icmple	72
   68:	iconst_3
   69:	goto	73
   72:	iload_1
   73:	iload_2
   74:	invokespecial	#146; //Method _Jack2_44:(II)Z
   77:	putfield	#252; //Field cond:Z
   80:	aload_0
   81:	iload_1
   82:	putfield	#289; //Field la:I
   85:	aload_0
   86:	iload_2
   87:	putfield	#281; //Field index:I
   90:	aload_0
   91:	getfield	#252; //Field cond:Z
   94:	ifeq	102
   97:	aload_0
   98:	invokespecial	#200; //Method _Jack3_44:()V
   101:	return
   102:	aload_0
   103:	getfield	#289; //Field la:I
   106:	istore_1
   107:	aload_0
   108:	getfield	#281; //Field index:I
   111:	istore_2
   112:	aload_0
   113:	aload_0
   114:	iload_1
   115:	iconst_3
   116:	if_icmple	123
   119:	iconst_3
   120:	goto	124
   123:	iload_1
   124:	iload_2
   125:	invokespecial	#147; //Method _Jack2_45:(II)Z
   128:	putfield	#252; //Field cond:Z
   131:	aload_0
   132:	iload_1
   133:	putfield	#289; //Field la:I
   136:	aload_0
   137:	iload_2
   138:	putfield	#281; //Field index:I
   141:	aload_0
   142:	getfield	#252; //Field cond:Z
   145:	ifeq	153
   148:	aload_0
   149:	invokespecial	#201; //Method _Jack3_45:()V
   152:	return
   153:	aload_0
   154:	getfield	#289; //Field la:I
   157:	istore_1
   158:	aload_0
   159:	getfield	#281; //Field index:I
   162:	istore_2
   163:	aload_0
   164:	aload_0
   165:	iload_1
   166:	iconst_3
   167:	if_icmple	174
   170:	iconst_3
   171:	goto	175
   174:	iload_1
   175:	iload_2
   176:	invokespecial	#148; //Method _Jack2_46:(II)Z
   179:	putfield	#252; //Field cond:Z
   182:	aload_0
   183:	iload_1
   184:	putfield	#289; //Field la:I
   187:	aload_0
   188:	iload_2
   189:	putfield	#281; //Field index:I
   192:	aload_0
   193:	getfield	#252; //Field cond:Z
   196:	ifeq	204
   199:	aload_0
   200:	invokespecial	#202; //Method _Jack3_46:()V
   203:	return
   204:	aload_0
   205:	getfield	#262; //Field efalse:Lspec/benchmarks/_228_jack/FalseException;
   208:	athrow

private void _Jack3character_list();
   throws spec/benchmarks/_228_jack/TrueException, spec/benchmarks/_228_jack/FalseException
  Code:
   0:	aload_0
   1:	getfield	#289; //Field la:I
   4:	istore_1
   5:	aload_0
   6:	getfield	#281; //Field index:I
   9:	istore_2
   10:	aload_0
   11:	aload_0
   12:	iload_1
   13:	iconst_3
   14:	if_icmple	21
   17:	iconst_3
   18:	goto	22
   21:	iload_1
   22:	iload_2
   23:	invokespecial	#154; //Method _Jack2_51:(II)Z
   26:	putfield	#252; //Field cond:Z
   29:	aload_0
   30:	iload_1
   31:	putfield	#289; //Field la:I
   34:	aload_0
   35:	iload_2
   36:	putfield	#281; //Field index:I
   39:	aload_0
   40:	getfield	#252; //Field cond:Z
   43:	ifeq	50
   46:	aload_0
   47:	invokespecial	#208; //Method _Jack3_51:()V
   50:	aload_0
   51:	bipush	72
   53:	invokespecial	#313; //Method scan_token:(I)V
   56:	aload_0
   57:	getfield	#289; //Field la:I
   60:	istore_1
   61:	aload_0
   62:	getfield	#281; //Field index:I
   65:	istore_2
   66:	aload_0
   67:	aload_0
   68:	iload_1
   69:	iconst_3
   70:	if_icmple	77
   73:	iconst_3
   74:	goto	78
   77:	iload_1
   78:	iload_2
   79:	invokespecial	#155; //Method _Jack2_52:(II)Z
   82:	putfield	#252; //Field cond:Z
   85:	aload_0
   86:	iload_1
   87:	putfield	#289; //Field la:I
   90:	aload_0
   91:	iload_2
   92:	putfield	#281; //Field index:I
   95:	aload_0
   96:	getfield	#252; //Field cond:Z
   99:	ifeq	106
   102:	aload_0
   103:	invokespecial	#209; //Method _Jack3_52:()V
   106:	aload_0
   107:	bipush	73
   109:	invokespecial	#313; //Method scan_token:(I)V
   112:	return

private void _Jack3character_descriptor();
   throws spec/benchmarks/_228_jack/TrueException, spec/benchmarks/_228_jack/FalseException
  Code:
   0:	aload_0
   1:	invokespecial	#231; //Method _Jack3string_literal:()V
   4:	aload_0
   5:	getfield	#289; //Field la:I
   8:	istore_1
   9:	aload_0
   10:	getfield	#281; //Field index:I
   13:	istore_2
   14:	aload_0
   15:	aload_0
   16:	iload_1
   17:	iconst_3
   18:	if_icmple	25
   21:	iconst_3
   22:	goto	26
   25:	iload_1
   26:	iload_2
   27:	invokespecial	#157; //Method _Jack2_54:(II)Z
   30:	putfield	#252; //Field cond:Z
   33:	aload_0
   34:	iload_1
   35:	putfield	#289; //Field la:I
   38:	aload_0
   39:	iload_2
   40:	putfield	#281; //Field index:I
   43:	aload_0
   44:	getfield	#252; //Field cond:Z
   47:	ifeq	54
   50:	aload_0
   51:	invokespecial	#211; //Method _Jack3_54:()V
   54:	return

}

